<?xml version="1.0" encoding="UTF-8"?>
<list xmlns:xsi="http://www.w3.org/2001/XMLSchema-instance" xsi:noNamespaceSchemaLocation="../../xsd/items.xsd">
	<item id="17600" type="EtcItem" nameRu="Записи Ада" nameEn="Scroll of Afterlife">
		<!-- Книга, содержащая душу древнего героя Гигантов. Используется перед Древней Статуей в Руинах Эсагира. -->
		<!-- Tome containing the soul of an Ancient Giant hero. Can be used before the Ancient Giat statues in the Reliquary of the Giants found in the Ruins of Ye Sagira. -->
		<set name="icon" val="icon.q10338_book_of_hades" />
		<set name="is_depositable" val="false" />
		<set name="is_tradable" val="false" />
		<set name="is_dropable" val="false" />
		<set name="is_destroyable" val="false" />
		<set name="is_sellable" val="false" />
		<set name="is_oly_restricted" val="true" />
		<set name="immediate_effect" val="1" />
		<set name="material" val="paper" />
	</item>
	<item id="17601" type="EtcItem" nameRu="Кусочек Сердца Земляного Червя" nameEn="Earth Wyrm Heart Fragment">
		<!-- Часть сердца убитого Земляного Червя. Все еще бьется. -->
		<!-- Cut heart of a dying Earth Wyrm's heart. It still moves and appears to contain tremendous life force. -->
		<set name="icon" val="icon.earthworm_heart" />
		<set name="is_tradable" val="false" />
		<set name="is_dropable" val="false" />
		<set name="is_sellable" val="false" />
		<set name="is_oly_restricted" val="true" />
		<set name="immediate_effect" val="1" />
		<set name="material" val="paper" />
	</item>
	<item id="17602" type="EtcItem" nameRu="Кристалл Жизненной Энергии" nameEn="Tissue Energy Crystal">
		<!-- Кристалл, добытый в окрестностях Семени Уничтожения. Его можно обменять у Кокрана. -->
		<!-- Crystal with concentrated tissue energy that can be obtained in the Seed of Annihilation. Bring it to Kirklan. -->
		<set name="icon" val="icon.high_star_stone_piece_i02" />
		<set name="is_tradable" val="false" />
		<set name="is_dropable" val="false" />
		<set name="is_sellable" val="false" />
		<set name="is_oly_restricted" val="true" />
		<set name="immediate_effect" val="1" />
		<set name="is_stackable" val="true" />
		<set name="material" val="crystal" />
	</item>
	<item id="17603" type="EtcItem" nameRu="Рецепт: Удобрение (100%)" nameEn="Recipe: Timiniel's Tonic">
		<!-- Для всех рас. Квестовый предмет. Рецепт создания удобрения для деревьев в Обители Тиминиэль. Требуется умение Создать Обычную Вещь 1-го уровня. Шанс создания: 100%.  -->
		<!-- Can be crafted by all races. Quest-type recipe. Recipe for making a tonic needed by the tree that is by Timiniel's side. Requires level 1 of the create command item skill. Success rate is 100%. -->
		<set name="icon" val="icon.etc_recipe_white_i00" />
		<set name="weight" val="30" />
		<set name="is_tradable" val="false" />
		<set name="is_dropable" val="false" />
		<set name="is_sellable" val="false" />
		<set name="default_action" val="recipe" />
		<set name="handler" val="Recipes" />
		<set name="immediate_effect" val="1" />
		<set name="is_stackable" val="true" />
		<set name="material" val="paper" />
	</item>
	<item id="17604" type="EtcItem" nameRu="Мерцающий Кристалл" nameEn="Glimmer Crystal">
		<!-- При использовании призывает Болотных Духов. -->
		<!-- Can gather nearby wisps when used. -->
		<set name="icon" val="icon.glimmer_crystal" />
		<set name="is_tradable" val="false" />
		<set name="is_dropable" val="false" />
		<set name="is_sellable" val="false" />
		<set name="is_oly_restricted" val="true" />
		<set name="reuse_delay" val="10000" />
		<set name="default_action" val="skill_reduce" />
		<set name="handler" val="ItemSkills" />
		<set name="is_stackable" val="true" />
		<set name="material" val="crystal" />
		<set name="item_skill" val="12001-1" />
		<!-- Glimmer Crystal -->
	</item>
	<item id="17605" type="EtcItem" nameRu="10 000 000 аден" nameEn="10,000,000 Adena">
		<!-- 10 000 000 аден. За такую сумму можно поцеловать даже жабу… -->
		<!-- 10,000,000 Adena. Coins received after kissing a toad... -->
		<set name="icon" val="icon.fairy_adena_joke" />
		<set name="is_tradable" val="false" />
		<set name="is_dropable" val="false" />
		<set name="is_sellable" val="false" />
		<set name="is_oly_restricted" val="true" />
		<set name="immediate_effect" val="1" />
		<set name="material" val="crystal" />
	</item>
	<item id="17606" type="EtcItem" nameRu="Обломок Крепости" nameEn="Stronghold Fragment">
		<!-- Часть Крепости, можно использовать в строительстве. -->
		<!-- Stronghold fragment piece for controlling the stronghold. -->
		<set name="icon" val="icon.gd_square_fragment" />
		<set name="is_tradable" val="false" />
		<set name="is_dropable" val="false" />
		<set name="is_sellable" val="false" />
		<set name="is_oly_restricted" val="true" />
		<set name="time" val="60" />
		<set name="default_action" val="skill_reduce" />
		<set name="handler" val="ItemSkills" />
		<set name="immediate_effect" val="1" />
		<set name="material" val="crystal" />
		<set name="item_skill" val="12003-1" />
		<!-- Stronghold Fragment -->
	</item>
	<item id="17607" type="EtcItem" nameRu="Ключи с Самоцветами" nameEn="Key to the Hall of Jewels">
		<!-- Связка ключей, позволяющих открыть все двери в Коралловом Саду.  -->
		<!-- Can open all the doors in the Coral Garden Hall. -->
		<set name="icon" val="icon.etc_key_i00" />
		<set name="is_destroyable" val="false" />
		<set name="is_oly_restricted" val="true" />
		<!-- <set name="commissionItemType" val="OTHER_ITEM" \> -->
		<set name="default_action" val="skill_reduce" />
		<set name="handler" val="ItemSkills" />
		<set name="immediate_effect" val="1" />
		<set name="material" val="crystal" />
		<set name="item_skill" val="12010-1" />
		<!-- Bonus Hall Key -->
	</item>
	<item id="17608" type="EtcItem" nameRu="Устройство Контроля Энергии" nameEn="Energy Control Device">
		<!-- Позволяет контролировать потоки энергии, когда это необходимо. -->
		<!-- You can control the amount of energy with this device. -->
		<set name="icon" val="icon.etc_medicine_of_growth_i00" />
		<set name="is_tradable" val="false" />
		<set name="is_dropable" val="false" />
		<set name="is_sellable" val="false" />
		<set name="is_oly_restricted" val="true" />
		<set name="default_action" val="skill_reduce" />
		<set name="handler" val="ItemSkills" />
		<set name="material" val="crystal" />
		<set name="item_skill" val="14224-1" />
		<!-- Energy Control Device -->
	</item>
	<item id="17609" type="Armor" nameRu="(Не используется) Ожерелье Истхины" nameEn="Istina's Necklace">
		<!-- (Не используется) Ожерелье Истхины (Нужно обсудить эффект) -->
		<!-- (Not in Use) Istina's Necklace. (needs effect calculation) -->
		<set name="icon" val="icon.accessary_queen_of_ice_necklace_i00" />
		<set name="default_action" val="equip" />
		<set name="bodypart" val="neck" />
		<set name="crystal_type" val="s80" />
		<set name="crystal_count" val="486" />
		<set name="weight" val="150" />
		<set name="enchant_enabled" val="1" />
		<!-- <set name="commissionItemType" val="NECKLACE" \> -->
		<set name="immediate_effect" val="1" />
		<set name="price" val="15192000" />
		<set name="material" val="silver" />
		<set name="item_skill" val="8459-1" />
		<!-- Freya's Necklace -->
		<for>
			<add order="0x10" stat="mDef" val="125" />
		</for>
	</item>
	<item id="17610" type="EtcItem" nameRu="Конденсат Жизненной Энергии" nameEn="Tissue Energy Residue">
		<!-- Конденсат, возникающий при использовании Жизненной Энергии. Отнесите этот предмет Солдату Таю. -->
		<!-- Tissue energy's residue. Bring it to Soldier Ty. -->
		<set name="icon" val="icon.etc_bark_green_i00" />
		<set name="is_tradable" val="false" />
		<set name="is_dropable" val="false" />
		<set name="is_sellable" val="false" />
		<set name="is_oly_restricted" val="true" />
		<set name="immediate_effect" val="1" />
		<set name="is_stackable" val="true" />
		<set name="material" val="crystal" />
	</item>
	<item id="17611" type="EtcItem" nameRu="Огромное Ядро" nameEn="Giant Cannonball">
		<!-- Используется для пушек, установленных в Тюрьме Изгнанников Тьмы. -->
		<!-- Can fire the cannon inside the Prison of Darkness. -->
		<set name="icon" val="icon.mde_big_bullet" />
		<set name="is_tradable" val="false" />
		<set name="is_dropable" val="false" />
		<set name="is_sellable" val="false" />
		<set name="is_oly_restricted" val="true" />
		<set name="immediate_effect" val="1" />
		<set name="is_stackable" val="true" />
		<set name="material" val="crystal" />
	</item>
	<item id="17612" type="EtcItem" nameRu="Осколок Памяти" nameEn="Memory Fragment">
		<!-- Позволяет воздействовать на память Спасии, заключенной в Тюрьме Изгнанников Тьмы. -->
		<!-- Can experience the memories of Spezion, who is sealed inside the Prison of Darkness. -->
		<set name="icon" val="icon.mde_memory_fragment" />
		<set name="is_tradable" val="false" />
		<set name="is_dropable" val="false" />
		<set name="is_sellable" val="false" />
		<set name="is_oly_restricted" val="true" />
		<set name="immediate_effect" val="1" />
		<set name="is_stackable" val="true" />
		<set name="material" val="crystal" />
	</item>
	<item id="17613" type="EtcItem" nameRu="Осколок Утраченной Памяти" nameEn="Frightening Memory Fragment">
		<!-- Позволяет воздействовать на память Спасии, заключенной в Тюрьме Изгнанников Тьмы. -->
		<!-- Can experience the memories of Spezion, who is sealed inside the Prison of Darkness. -->
		<set name="icon" val="icon.mde_memory_fragment02" />
		<set name="is_tradable" val="false" />
		<set name="is_dropable" val="false" />
		<set name="is_sellable" val="false" />
		<set name="is_oly_restricted" val="true" />
		<set name="immediate_effect" val="1" />
		<set name="is_stackable" val="true" />
		<set name="material" val="crystal" />
	</item>
	<item id="17614" type="EtcItem" nameRu="Записи Пантеона" nameEn="Pantheon's Book">
		<!-- Можно посмотреть список героев. -->
		<!-- Can view the records of the heroes. -->
		<set name="icon" val="icon.si_phanteon_book" />
		<set name="is_tradable" val="false" />
		<set name="is_dropable" val="false" />
		<set name="is_destroyable" val="false" />
		<set name="is_sellable" val="false" />
		<set name="is_oly_restricted" val="true" />
		<set name="immediate_effect" val="1" />
		<set name="material" val="crystal" />
	</item>
	<item id="17615" type="EtcItem" nameRu="Знак Беллис" nameEn="Belis' Mark">
		<!-- Используется в Лабиринте Беллис. -->
		<!-- Can use the Labyrinth of Belis. -->
		<set name="icon" val="icon.bel_mark_clear" />
		<set name="is_tradable" val="false" />
		<set name="is_dropable" val="false" />
		<set name="is_sellable" val="false" />
		<set name="is_oly_restricted" val="true" />
		<set name="immediate_effect" val="1" />
		<set name="is_stackable" val="true" />
		<set name="material" val="crystal" />
	</item>
	<item id="17616" type="EtcItem" nameRu="Свеча Души" nameEn="Soul Candle">
		<!-- Собирайте Свечи Души. -->
		<!-- Collect the soul candles. -->
		<set name="icon" val="icon.darkelf_campaign_candle" />
		<set name="is_tradable" val="false" />
		<set name="is_sellable" val="false" />
		<set name="is_oly_restricted" val="true" />
		<set name="immediate_effect" val="1" />
		<set name="is_stackable" val="true" />
		<set name="material" val="crystal" />
	</item>
	<item id="17617" type="EtcItem" nameRu="Шкатулка с Самоцветами" nameEn="Jewel Box">
		<!-- Собирайте шкатулки с Самоцветами, которые можно использовать в особом задании. -->
		<!-- Used during the Searching for the Jewels campaign. Collect a lot. -->
		<set name="icon" val="icon.darkelf_campaign_box" />
		<set name="is_tradable" val="false" />
		<set name="is_dropable" val="false" />
		<set name="is_destroyable" val="false" />
		<set name="is_sellable" val="false" />
		<set name="is_oly_restricted" val="true" />
		<set name="immediate_effect" val="1" />
		<set name="is_stackable" val="true" />
		<set name="material" val="crystal" />
	</item>
	<item id="17618" type="EtcItem" nameRu="Карта Фортуны" nameEn="Fortuna Map">
		<!-- Старинная карта. Больше узнать о ней можно у Изшаэля в Древнем Городе Аркан. -->
		<!-- Old map. Bring it to Izael, who knows a lot about Ancient Arcan, and ask about it. -->
		<set name="icon" val="icon.fortuna_enter" />
		<set name="is_oly_restricted" val="true" />
		<!-- <set name="commissionItemType" val="OTHER_ITEM" \> -->
		<set name="immediate_effect" val="1" />
		<set name="is_stackable" val="true" />
		<set name="material" val="crystal" />
	</item>
	<item id="17619" type="EtcItem" nameRu="Устройство Поиска Сокровищ" nameEn="Relic Detector">
		<!-- Призывает особое устройство для обнаружения ценностей в Башне Крумы. -->
		<!-- Summon a relic-finding detector inside Cruma Tower. -->
		<set name="icon" val="icon.summon_object_finder" />
		<set name="is_depositable" val="false" />
		<set name="is_tradable" val="false" />
		<set name="is_dropable" val="false" />
		<set name="is_destroyable" val="false" />
		<set name="is_sellable" val="false" />
		<set name="is_oly_restricted" val="true" />
		<set name="reuse_delay" val="30000" />
		<set name="default_action" val="skill_reduce" />
		<set name="handler" val="ItemSkills" />
		<set name="immediate_effect" val="1" />
		<set name="is_stackable" val="true" />
		<set name="material" val="crystal" />
		<set name="item_skill" val="12004-1" />
		<!-- Summon Detector -->
	</item>
	<item id="17620" type="EtcItem" nameRu="Пестицид" nameEn="Insecticide">
		<!-- Эффект можно увидеть, распылив на соответствующие типы насекомых. -->
		<!-- It is effective when used on the eggs of the correct type insect. -->
		<set name="icon" val="icon.bug_spray_a" />
		<set name="is_tradable" val="false" />
		<set name="is_dropable" val="false" />
		<set name="is_sellable" val="false" />
		<set name="is_oly_restricted" val="true" />
		<set name="default_action" val="skill_reduce" />
		<set name="handler" val="ItemSkills" />
		<set name="immediate_effect" val="1" />
		<set name="is_stackable" val="true" />
		<set name="material" val="crystal" />
		<set name="item_skill" val="12005-1" />
		<!-- Spray Insecticide -->
	</item>
	<item id="17621" type="EtcItem" nameRu="Пестицид" nameEn="Insecticide">
		<!-- Эффект можно увидеть, распылив на соответствующие типы насекомых. -->
		<!-- It is effective when used on the eggs of the correct type insect. -->
		<set name="icon" val="icon.bug_spray_b" />
		<set name="is_tradable" val="false" />
		<set name="is_dropable" val="false" />
		<set name="is_sellable" val="false" />
		<set name="is_oly_restricted" val="true" />
		<set name="default_action" val="skill_reduce" />
		<set name="handler" val="ItemSkills" />
		<set name="immediate_effect" val="1" />
		<set name="is_stackable" val="true" />
		<set name="material" val="crystal" />
		<set name="item_skill" val="12006-1" />
		<!-- Spray Insecticide -->
	</item>
	<item id="17622" type="EtcItem" nameRu="Пестицид" nameEn="Insecticide">
		<!-- Эффект можно увидеть, распылив на соответствующие типы насекомых. -->
		<!-- It is effective when used on the eggs of the correct type insect. -->
		<set name="icon" val="icon.bug_spray_c" />
		<set name="is_tradable" val="false" />
		<set name="is_dropable" val="false" />
		<set name="is_sellable" val="false" />
		<set name="is_oly_restricted" val="true" />
		<set name="default_action" val="skill_reduce" />
		<set name="handler" val="ItemSkills" />
		<set name="immediate_effect" val="1" />
		<set name="is_stackable" val="true" />
		<set name="material" val="crystal" />
		<set name="item_skill" val="12007-1" />
		<!-- Spray Insecticide -->
	</item>
	<item id="17623" type="Armor" nameRu="Кольцо Земляного Червя" nameEn="Earth Wyrm Heart Ring">
		<!-- MP +38, увеличивает сопротивление физ./ маг. отрицательным эффектам, Скор. Восстановления MP, силу Физ. Крит. Атк., Физ. Точность. Сопротивление отравлению +50%, шанс отравления +50%, сопротивление отталкиванию, опрокидыванию, притягиванию, атакам уязвимых мест +20%. Увеличивает Скор. Атк./ Скор. Маг., сопротивление ветру/ воде. Увеличивает Скор. Атк./ Скор. Маг., шанс Маг. Крит. Атк. членов группы и дарует им эффект Гнева Вампира. При одновременном ношении двух колец эффект не суммируется. -->
		<!-- MP +38, P./ M. Debuff Resistance +15, MP Regeneration +3, P. Critical Damage +20%, and P. Accuracy +5. Poison Resistance +50%, Poison Atk. Rate +50%, Knock Back, Knock Down, Pulling, Danger Zone Resistance +20%, Atk. Spd. and Casting Spd. +6%, and Wind/ Water Resistance +30. Can use skills that affect party members' Atk. Spd., Casting Spd., and Vampiric Rage. Can use Poison removal. Only one effect is applied when two of the same rings are equipped. -->
		<set name="icon" val="icon.ring_earthworm_heart" />
		<set name="default_action" val="equip" />
		<set name="bodypart" val="rfinger;lfinger" />
		<set name="crystal_type" val="s84" />
		<set name="crystal_count" val="324" />
		<set name="weight" val="150" />
		<set name="price" val="15192000" />
		<set name="enchant_enabled" val="1" />
		<set name="equip_reuse_delay" val="7200" />
		<set name="immediate_effect" val="1" />
		<!-- <set name="commissionItemType" val="RING" \> -->
		<set name="material" val="silver" />
		<set name="item_skill" val="13318-1" />
		<!-- Earth Wyrm Heart Ring -->
		<set name="item_skill" val="13319-1" />
		<!-- Earth Wyrm Heart Ring -->
		<set name="item_skill" val="13317-1" />
		<!-- Earth Wyrm Heart Ring -->
		<for>
			<add order="0x10" stat="mDef" val="108" />
		</for>
	</item>
	<item id="17624" type="EtcItem" nameRu="Символ Дерзости" nameEn="Token of Insolence Tower">
		<!-- Данный символ можно обменять на квестовые предметы Башни Дерзости. -->
		<!-- Token that can be exchanged for a Tower of Insolence item. -->
		<set name="icon" val="icon.token_of_oman" />
		<set name="is_tradable" val="false" />
		<set name="is_dropable" val="false" />
		<set name="is_sellable" val="false" />
		<set name="immediate_effect" val="1" />
		<set name="is_stackable" val="true" />
		<set name="material" val="paper" />
	</item>
	<item id="17625" type="EtcItem" nameRu="Краска Гигантов Ур. 1 - СИЛ" nameEn="Lv. 1 Giant STR Dye">
		<!-- Краска СИЛ Гигантов Ур. 1 (СИЛ+3 ЛВК-2). Если отдать 10 флаконов этой краски Мастеру Татуировок, то персонаж получит татуировку, изменяющую его характеристики. Требования: Все классы после перерождения и 3-го освобождения. -->
		<!-- Lv. 1 Giant STR Dye (Str +3 Dex -2). Collect and take 10 units of this magical dye to the symbol maker in town and you will receive a symbol that boosts your abilities. Can be used after Awakening, or 3rd Liberation. All classes. -->
		<set name="icon" val="icon.lv1_1_dye_str" />
		<set name="weight" val="150" />
		<set name="price" val="488300" />
		<set name="is_stackable" val="true" />
		<set name="etcitem_type" val="dye" />
		<set name="immediate_effect" val="1" />
		<!-- <set name="commissionItemType" val="DYES" \> -->
		<set name="material" val="liquid" />
	</item>
	<item id="17626" type="EtcItem" nameRu="Краска Гигантов Ур. 1 - ЛВК" nameEn="Lv. 1 Giant DEX Dye">
		<!-- Краска ЛВК Гигантов Ур. 1 (ЛВК+3 ВЫН-2). Если отдать 10 флаконов этой краски Мастеру Татуировок, то персонаж получит татуировку, изменяющую его характеристики. Требования: Все классы после перерождения и 3-го освобождения. -->
		<!-- Lv. 1 Giant DEX Dye (Dex +3 Con -2). Collect and take 10 units of this magical dye to the symbol maker in town and you will receive a symbol that boosts your abilities. Can be used after Awakening, or 3rd Liberation. All classes. -->
		<set name="icon" val="icon.lv1_1_dye_dex" />
		<set name="weight" val="150" />
		<set name="price" val="488300" />
		<set name="is_stackable" val="true" />
		<set name="etcitem_type" val="dye" />
		<set name="immediate_effect" val="1" />
		<!-- <set name="commissionItemType" val="DYES" \> -->
		<set name="material" val="liquid" />
	</item>
	<item id="17627" type="EtcItem" nameRu="Краска Гигантов Ур. 1 - ВЫН" nameEn="Lv. 1 Giant CON Dye">
		<!-- Краска ВЫН Гигантов Ур. 1 (ВЫН+3 СИЛ-2). Если отдать 10 флаконов этой краски Мастеру Татуировок, то персонаж получит татуировку, изменяющую его характеристики. Требования: Все классы после перерождения и 3-го освобождения. -->
		<!-- Lv. 1 Giant CON Dye (Con +3 Str -2). Collect and take 10 units of this magical dye to the symbol maker in town and you will receive a symbol that boosts your abilities. Can be used after Awakening, or 3rd Liberation. All classes. -->
		<set name="icon" val="icon.lv1_1_dye_con" />
		<set name="weight" val="150" />
		<set name="price" val="488300" />
		<set name="is_stackable" val="true" />
		<set name="etcitem_type" val="dye" />
		<set name="immediate_effect" val="1" />
		<!-- <set name="commissionItemType" val="DYES" \> -->
		<set name="material" val="liquid" />
	</item>
	<item id="17628" type="EtcItem" nameRu="Краска Гигантов Ур. 1 - ИНТ" nameEn="Lv. 1 Giant INT Dye">
		<!-- Краска ИНТ Гигантов Ур. 1 (ИНТ+3 МДР-2). Если отдать 10 флаконов этой краски Мастеру Татуировок, то персонаж получит татуировку, изменяющую его характеристики. Требования: Все классы после перерождения и 3-го освобождения. -->
		<!-- Lv. 1 Giant INT Dye (Int +3 Wit -2). Collect and take 10 units of this magical dye to the symbol maker in town and you will receive a symbol that boosts your abilities. Can be used after Awakening, or 3rd Liberation. All classes. -->
		<set name="icon" val="icon.lv1_1_dye_int" />
		<set name="weight" val="150" />
		<set name="price" val="488300" />
		<set name="is_stackable" val="true" />
		<set name="etcitem_type" val="dye" />
		<set name="immediate_effect" val="1" />
		<!-- <set name="commissionItemType" val="DYES" \> -->
		<set name="material" val="liquid" />
	</item>
	<item id="17629" type="EtcItem" nameRu="Краска Гигантов Ур. 1 - МДР" nameEn="Lv. 1 Giant WIT Dye">
		<!-- Краска МДР Гигантов Ур. 1 (МДР+3 ДУХ-2). Если отдать 10 флаконов этой краски Мастеру Татуировок, то персонаж получит татуировку, изменяющую его характеристики. Требования: Все классы после перерождения и 3-го освобождения. -->
		<!-- Lv. 1 Giant WIT Dye (Wit +3 Men -2). Collect and take 10 units of this magical dye to the symbol maker in town and you will receive a symbol that boosts your abilities. Can be used after Awakening, or 3rd Liberation. All classes. -->
		<set name="icon" val="icon.lv1_1_dye_wit" />
		<set name="weight" val="150" />
		<set name="price" val="488300" />
		<set name="is_stackable" val="true" />
		<set name="etcitem_type" val="dye" />
		<set name="immediate_effect" val="1" />
		<!-- <set name="commissionItemType" val="DYES" \> -->
		<set name="material" val="liquid" />
	</item>
	<item id="17630" type="EtcItem" nameRu="Краска Гигантов Ур. 1 - ДУХ" nameEn="Lv. 1 Giant MEN Dye">
		<!-- Краска ДУХ Гигантов Ур. 1 (ДУХ+3 ИНТ-2). Если отдать 10 флаконов этой краски Мастеру Татуировок, то персонаж получит татуировку, изменяющую его характеристики. Требования: Все классы после перерождения и 3-го освобождения. -->
		<!-- Lv. 1 Giant MEN Dye (Men +3 Int -2). Collect and take 10 units of this magical dye to the symbol maker in town and you will receive a symbol that boosts your abilities. Can be used after Awakening, or 3rd Liberation. All classes. -->
		<set name="icon" val="icon.lv1_1_dye_men" />
		<set name="weight" val="150" />
		<set name="price" val="488300" />
		<!-- <set name="commissionItemType" val="DYES" \> -->
		<set name="etcitem_type" val="dye" />
		<set name="immediate_effect" val="1" />
		<set name="is_stackable" val="true" />
		<set name="material" val="liquid" />
	</item>
	<item id="17631" type="EtcItem" nameRu="Древняя Краска Ур. 1 - СИЛ" nameEn="Lv. 1 Ancient STR Dye">
		<!-- Древняя краска СИЛ Ур. 1 (СИЛ+3 ЛВК-2 Сопротивление огню +5). Если отдать 10 флаконов этой краски Мастеру Татуировок, то персонаж получит татуировку, изменяющую его характеристики. Требования: Все классы после перерождения и 3-го освобождения. -->
		<!-- Lv. 1 Giant STR Dye (Str +3 Dex -2 Fire Resistance +5). Collect and take 10 units of this magical dye to the symbol maker in town and you will receive a symbol that boosts your abilities. Can be used after Awakening, or 3rd Liberation. All classes. -->
		<set name="icon" val="icon.lv1_2_dye_str" />
		<set name="weight" val="150" />
		<set name="price" val="692400" />
		<set name="is_stackable" val="true" />
		<set name="etcitem_type" val="dye" />
		<set name="immediate_effect" val="1" />
		<!-- <set name="commissionItemType" val="DYES" \> -->
		<set name="material" val="liquid" />
	</item>
	<item id="17632" type="EtcItem" nameRu="Древняя Краска Ур. 1 - ЛВК" nameEn="Lv. 1 Ancient DEX Dye">
		<!-- Древняя краска ЛВК Ур. 1 (ЛВК+3 ВЫН-2 Сопротивление земле +5). Если отдать 10 флаконов этой краски Мастеру Татуировок, то персонаж получит татуировку, изменяющую его характеристики. Требования: Все классы после перерождения и 3-го освобождения. -->
		<!-- Lv. 1 Giant DEX Dye (Dex +3 Con -2 Earth Resistance +5). Collect and take 10 units of this magical dye to the symbol maker in town and you will receive a symbol that boosts your abilities. Can be used after Awakening, or 3rd Liberation. All classes. -->
		<set name="icon" val="icon.lv1_2_dye_dex" />
		<set name="weight" val="150" />
		<set name="price" val="692400" />
		<set name="is_stackable" val="true" />
		<set name="etcitem_type" val="dye" />
		<set name="immediate_effect" val="1" />
		<!-- <set name="commissionItemType" val="DYES" \> -->
		<set name="material" val="liquid" />
	</item>
	<item id="17633" type="EtcItem" nameRu="Древняя Краска Ур. 1 - ВЫН" nameEn="Lv. 1 Ancient CON Dye">
		<!-- Древняя краска ВЫН Ур. 1 (ВЫН+3 СИЛ-2 Сопротивление тьме +5). Если отдать 10 флаконов этой краски Мастеру Татуировок, то персонаж получит татуировку, изменяющую его характеристики. Требования: Все классы после перерождения и 3-го освобождения. -->
		<!-- Lv. 1 Giant CON Dye (Con +3 Str -2 Dark Resistance +5). Collect and take 10 units of this magical dye to the symbol maker in town and you will receive a symbol that boosts your abilities. Can be used after Awakening, or 3rd Liberation. All classes. -->
		<set name="icon" val="icon.lv1_2_dye_con" />
		<set name="weight" val="150" />
		<set name="price" val="692400" />
		<set name="is_stackable" val="true" />
		<set name="etcitem_type" val="dye" />
		<set name="immediate_effect" val="1" />
		<!-- <set name="commissionItemType" val="DYES" \> -->
		<set name="material" val="liquid" />
	</item>
	<item id="17634" type="EtcItem" nameRu="Древняя Краска Ур. 1 - ИНТ" nameEn="Lv. 1 Ancient INT Dye">
		<!-- Древняя краска ИНТ Ур. 1 (ИНТ+3 МДР-2 Сопротивление воде +5). Если отдать 10 флаконов этой краски Мастеру Татуировок, то персонаж получит татуировку, изменяющую его характеристики. Требования: Все классы после перерождения и 3-го освобождения. -->
		<!-- Lv. 1 Giant INT Dye (Int +3 Wit -2 Water Resistance +5). Collect and take 10 units of this magical dye to the symbol maker in town and you will receive a symbol that boosts your abilities. Can be used after Awakening, or 3rd Liberation. All classes. -->
		<set name="icon" val="icon.lv1_2_dye_int" />
		<set name="weight" val="150" />
		<set name="price" val="692400" />
		<set name="is_stackable" val="true" />
		<set name="etcitem_type" val="dye" />
		<set name="immediate_effect" val="1" />
		<!-- <set name="commissionItemType" val="DYES" \> -->
		<set name="material" val="liquid" />
	</item>
	<item id="17635" type="EtcItem" nameRu="Древняя Краска Ур. 1 - МДР" nameEn="Lv. 1 Ancient WIT Dye">
		<!-- Древняя краска МДР Ур. 1 (МДР+3 ДУХ-2 Сопротивление ветру +5). Если отдать 10 флаконов этой краски Мастеру Татуировок, то персонаж получит татуировку, изменяющую его характеристики. Требования: Все классы после перерождения и 3-го освобождения. -->
		<!-- Lv. 1 Giant WIT Dye (Wit +3 Men -2 Wind Resistance +5). Collect and take 10 units of this magical dye to the symbol maker in town and you will receive a symbol that boosts your abilities. Can be used after Awakening, or 3rd Liberation. All classes. -->
		<set name="icon" val="icon.lv1_2_dye_wit" />
		<set name="weight" val="150" />
		<set name="price" val="692400" />
		<set name="is_stackable" val="true" />
		<set name="etcitem_type" val="dye" />
		<set name="immediate_effect" val="1" />
		<!-- <set name="commissionItemType" val="DYES" \> -->
		<set name="material" val="liquid" />
	</item>
	<item id="17636" type="EtcItem" nameRu="Древняя Краска Ур. 1 - ДУХ" nameEn="Lv. 1 Ancient MEN Dye">
		<!-- Древняя краска ДУХ Ур. 1 (ДУХ+3 ИНТ-2 Сопротивление святости +5). Если отдать 10 флаконов этой краски Мастеру Татуировок, то персонаж получит татуировку, изменяющую его характеристики. Требования: Все классы после перерождения и 3-го освобождения. -->
		<!-- Lv. 1 Giant MEN Dye (Men +3 Int -2 Holy Resistance +5). Collect and take 10 units of this magical dye to the symbol maker in town and you will receive a symbol that boosts your abilities. Can be used after Awakening, or 3rd Liberation. All classes. -->
		<set name="icon" val="icon.lv1_2_dye_men" />
		<set name="weight" val="150" />
		<set name="price" val="692400" />
		<!-- <set name="commissionItemType" val="DYES" \> -->
		<set name="etcitem_type" val="dye" />
		<set name="immediate_effect" val="1" />
		<set name="is_stackable" val="true" />
		<set name="material" val="liquid" />
	</item>
	<item id="17637" type="EtcItem" nameRu="Легендарная Краска Ур. 1 - СИЛ" nameEn="Lv. 1 Legendary STR Dye">
		<!-- Легендарная краска СИЛ Ур. 1 (СИЛ+3 ЛВК-1 Сопротивление огню +5). Если отдать 10 флаконов этой краски Мастеру Татуировок, то персонаж получит татуировку, изменяющую его характеристики. Требования: Все классы после перерождения и 3-го освобождения. -->
		<!-- Lv. 1 Legendary STR Dye (Str +3 Dex -1 Fire Resistance +5). Collect and take 10 units of this magical dye to the symbol maker in town and you will receive a symbol that boosts your abilities. Can be used after Awakening, or 3rd Liberation. All classes. -->
		<set name="icon" val="icon.lv1_3_dye_str" />
		<set name="weight" val="150" />
		<set name="price" val="896400" />
		<set name="is_stackable" val="true" />
		<set name="etcitem_type" val="dye" />
		<set name="immediate_effect" val="1" />
		<!-- <set name="commissionItemType" val="DYES" \> -->
		<set name="material" val="liquid" />
	</item>
	<item id="17638" type="EtcItem" nameRu="Легендарная Краска Ур. 1 - ЛВК" nameEn="Lv. 1 Legendary DEX Dye">
		<!-- Легендарная краска ЛВК Ур. 1 (ЛВК+3 ВЫН-1 Сопротивление земле +5). Если отдать 10 флаконов этой краски Мастеру Татуировок, то персонаж получит татуировку, изменяющую его характеристики. Требования: Все классы после перерождения и 3-го освобождения. -->
		<!-- Lv. 1 Legendary DEX Dye (Dex +3 Con -1 Earth Resistance +5). Collect and take 10 units of this magical dye to the symbol maker in town and you will receive a symbol that boosts your abilities. Can be used after Awakening, or 3rd Liberation. All classes. -->
		<set name="icon" val="icon.lv1_3_dye_dex" />
		<set name="weight" val="150" />
		<set name="price" val="896400" />
		<set name="is_stackable" val="true" />
		<set name="etcitem_type" val="dye" />
		<set name="immediate_effect" val="1" />
		<!-- <set name="commissionItemType" val="DYES" \> -->
		<set name="material" val="liquid" />
	</item>
	<item id="17639" type="EtcItem" nameRu="Легендарная Краска Ур. 1 - ВЫН" nameEn="Lv. 1 Legendary CON Dye">
		<!-- Легендарная краска ВЫН Ур. 1 (ВЫН+3 СИЛ-1 Сопротивление тьме +5). Если отдать 10 флаконов этой краски Мастеру Татуировок, то персонаж получит татуировку, изменяющую его характеристики. Требования: Все классы после перерождения и 3-го освобождения. -->
		<!-- Lv. 1 Legendary CON Dye (Con +3 Str -1 Dark Resistance +5). Collect and take 10 units of this magical dye to the symbol maker in town and you will receive a symbol that boosts your abilities. Can be used after Awakening, or 3rd Liberation. All classes. -->
		<set name="icon" val="icon.lv1_3_dye_con" />
		<set name="weight" val="150" />
		<set name="price" val="896400" />
		<set name="is_stackable" val="true" />
		<set name="etcitem_type" val="dye" />
		<set name="immediate_effect" val="1" />
		<!-- <set name="commissionItemType" val="DYES" \> -->
		<set name="material" val="liquid" />
	</item>
	<item id="17640" type="EtcItem" nameRu="Легендарная Краска Ур. 1 - ИНТ" nameEn="Lv. 1 Legendary INT Dye">
		<!-- Легендарная краска ИНТ Ур. 1 (ИНТ+3 МДР-1 Сопротивление воде +5). Если отдать 10 флаконов этой краски Мастеру Татуировок, то персонаж получит татуировку, изменяющую его характеристики. Требования: Все классы после перерождения и 3-го освобождения. -->
		<!-- Lv. 1 Legendary INT Dye (Int +3 Wit -1 Water Resistance +5). Collect and take 10 units of this magical dye to the symbol maker in town and you will receive a symbol that boosts your abilities. Can be used after Awakening, or 3rd Liberation. All classes. -->
		<set name="icon" val="icon.lv1_3_dye_int" />
		<set name="weight" val="150" />
		<set name="price" val="896400" />
		<set name="is_stackable" val="true" />
		<set name="etcitem_type" val="dye" />
		<set name="immediate_effect" val="1" />
		<!-- <set name="commissionItemType" val="DYES" \> -->
		<set name="material" val="liquid" />
	</item>
	<item id="17641" type="EtcItem" nameRu="Легендарная Краска Ур. 1 - МДР" nameEn="Lv. 1 Legendary WIT Dye">
		<!-- Легендарная краска МДР Ур. 1 (МДР+3 ДУХ-1 Сопротивление ветру +5). Если отдать 10 флаконов этой краски Мастеру Татуировок, то персонаж получит татуировку, изменяющую его характеристики. Требования: Все классы после перерождения и 3-го освобождения. -->
		<!-- Lv. 1 Legendary WIT Dye (Wit +3 Men -1 Wind Resistance +5). Collect and take 10 units of this magical dye to the symbol maker in town and you will receive a symbol that boosts your abilities. Equipping 2 will only give the effect of 1 for Attribute Resistance. Can be used after Awakening, or 3rd Liberation. All classes. -->
		<set name="icon" val="icon.lv1_3_dye_wit" />
		<set name="weight" val="150" />
		<set name="price" val="896400" />
		<set name="is_stackable" val="true" />
		<set name="etcitem_type" val="dye" />
		<set name="immediate_effect" val="1" />
		<!-- <set name="commissionItemType" val="DYES" \> -->
		<set name="material" val="liquid" />
	</item>
	<item id="17642" type="EtcItem" nameRu="Легендарная Краска Ур. 1 - ДУХ" nameEn="Lv. 1 Legendary MEN Dye">
		<!-- Легендарная краска ДУХ Ур. 1 (ДУХ+3 ИНТ-1 Сопротивление святости +5). Если отдать 10 флаконов этой краски Мастеру Татуировок, то персонаж получит татуировку, изменяющую его характеристики. Требования: Все классы после перерождения и 3-го освобождения. -->
		<!-- Lv. 1 Legendary MEN Dye (Men +3 Int -1 Holy Resistance +5). Collect and take 10 units of this magical dye to the symbol maker in town and you will receive a symbol that boosts your abilities. Can be used after Awakening, or 3rd Liberation. All classes. -->
		<set name="icon" val="icon.lv1_3_dye_men" />
		<set name="weight" val="150" />
		<set name="price" val="896400" />
		<!-- <set name="commissionItemType" val="DYES" \> -->
		<set name="etcitem_type" val="dye" />
		<set name="immediate_effect" val="1" />
		<set name="is_stackable" val="true" />
		<set name="material" val="liquid" />
	</item>
	<item id="17643" type="EtcItem" nameRu="Краска Гигантов Ур. 2 - СИЛ" nameEn="Lv. 2 Giant STR Dye">
		<!-- Краска СИЛ Гигантов Ур. 2 (СИЛ+4 ЛВК-3). Если отдать 10 флаконов этой краски Мастеру Татуировок, то персонаж получит татуировку, изменяющую его характеристики. Требования: Все классы после перерождения и 3-го освобождения. -->
		<!-- Lv. 2 Giant STR Dye (Str +4 Dex -3). Collect and take 10 units of this magical dye to the symbol maker in town and you will receive a symbol that boosts your abilities. Can be used after Awakening, or 3rd Liberation. All classes. -->
		<set name="icon" val="icon.lv2_1_dye_str" />
		<set name="weight" val="150" />
		<set name="price" val="1097700" />
		<!-- <set name="commissionItemType" val="DYES" \> -->
		<set name="etcitem_type" val="dye" />
		<set name="immediate_effect" val="1" />
		<set name="is_stackable" val="true" />
		<set name="material" val="liquid" />
	</item>
	<item id="17644" type="EtcItem" nameRu="Краска Гигантов Ур. 2 - ЛВК" nameEn="Lv. 2 Giant DEX Dye">
		<!-- Краска ЛВК Гигантов Ур. 2 (ЛВК+4 ВЫН-3). Если отдать 10 флаконов этой краски Мастеру Татуировок, то персонаж получит татуировку, изменяющую его характеристики. Требования: Все классы после перерождения и 3-го освобождения. -->
		<!-- Lv. 2 Giant DEX Dye (Dex +4 Con -3). Collect and take 10 units of this magical dye to the symbol maker in town and you will receive a symbol that boosts your abilities. Can be used after Awakening, or 3rd Liberation. All classes. -->
		<set name="icon" val="icon.lv2_1_dye_dex" />
		<set name="weight" val="150" />
		<set name="price" val="1097700" />
		<set name="is_stackable" val="true" />
		<set name="etcitem_type" val="dye" />
		<set name="immediate_effect" val="1" />
		<!-- <set name="commissionItemType" val="DYES" \> -->
		<set name="material" val="liquid" />
	</item>
	<item id="17645" type="EtcItem" nameRu="Краска Гигантов Ур. 2 - ВЫН" nameEn="Lv. 2 Giant CON Dye">
		<!-- Краска ВЫН Гигантов Ур. 2 (ВЫН+4 СИЛ-3). Если отдать 10 флаконов этой краски Мастеру Татуировок, то персонаж получит татуировку, изменяющую его характеристики. Требования: Все классы после перерождения и 3-го освобождения. -->
		<!-- Lv. 2 Giant CON Dye (Con +4 Str -3). Collect and take 10 units of this magical dye to the symbol maker in town and you will receive a symbol that boosts your abilities. Can be used after Awakening, or 3rd Liberation. All classes. -->
		<set name="icon" val="icon.lv2_1_dye_con" />
		<set name="weight" val="150" />
		<set name="price" val="1097700" />
		<!-- <set name="commissionItemType" val="DYES" \> -->
		<set name="etcitem_type" val="dye" />
		<set name="immediate_effect" val="1" />
		<set name="is_stackable" val="true" />
		<set name="material" val="liquid" />
	</item>
	<item id="17646" type="EtcItem" nameRu="Краска Гигантов Ур. 2 - ИНТ" nameEn="Lv. 2 Giant INT Dye">
		<!-- Краска ИНТ Гигантов Ур. 2 (ИНТ+4 МДР-3). Если отдать 10 флаконов этой краски Мастеру Татуировок, то персонаж получит татуировку, изменяющую его характеристики. Требования: Все классы после перерождения и 3-го освобождения. -->
		<!-- Lv. 2 Giant INT Dye (Int +4 Wit -3). Collect and take 10 units of this magical dye to the symbol maker in town and you will receive a symbol that boosts your abilities. Can be used after Awakening, or 3rd Liberation. All classes. -->
		<set name="icon" val="icon.lv2_1_dye_int" />
		<set name="weight" val="150" />
		<set name="price" val="1097700" />
		<set name="is_stackable" val="true" />
		<set name="etcitem_type" val="dye" />
		<set name="immediate_effect" val="1" />
		<!-- <set name="commissionItemType" val="DYES" \> -->
		<set name="material" val="liquid" />
	</item>
	<item id="17647" type="EtcItem" nameRu="Краска Гигантов Ур. 2 - МДР" nameEn="Lv. 2 Giant WIT Dye">
		<!-- Краска МДР Гигантов Ур. 2 (МДР+4 ДУХ-3). Если отдать 10 флаконов этой краски Мастеру Татуировок, то персонаж получит татуировку, изменяющую его характеристики. Требования: Все классы после перерождения и 3-го освобождения. -->
		<!-- Lv. 2 Giant WIT Dye (Wit +4 Men -3). Collect and take 10 units of this magical dye to the symbol maker in town and you will receive a symbol that boosts your abilities. Can be used after Awakening, or 3rd Liberation. All classes. -->
		<set name="icon" val="icon.lv2_1_dye_wit" />
		<set name="weight" val="150" />
		<set name="price" val="1097700" />
		<!-- <set name="commissionItemType" val="DYES" \> -->
		<set name="etcitem_type" val="dye" />
		<set name="immediate_effect" val="1" />
		<set name="is_stackable" val="true" />
		<set name="material" val="liquid" />
	</item>
	<item id="17648" type="EtcItem" nameRu="Краска Гигантов Ур. 2 - ДУХ" nameEn="Lv. 2 Giant MEN Dye">
		<!-- Краска ДУХ Гигантов Ур. 2 (ДУХ+4 ИНТ-3). Если отдать 10 флаконов этой краски Мастеру Татуировок, то персонаж получит татуировку, изменяющую его характеристики. Требования: Все классы после перерождения и 3-го освобождения. -->
		<!-- Lv. 2 Giant MEN Dye (Men +4 Int -3). Collect and take 10 units of this magical dye to the symbol maker in town and you will receive a symbol that boosts your abilities. Can be used after Awakening, or 3rd Liberation. All classes. -->
		<set name="icon" val="icon.lv2_1_dye_men" />
		<set name="weight" val="150" />
		<set name="price" val="1097700" />
		<!-- <set name="commissionItemType" val="DYES" \> -->
		<set name="etcitem_type" val="dye" />
		<set name="immediate_effect" val="1" />
		<set name="is_stackable" val="true" />
		<set name="material" val="liquid" />
	</item>
	<item id="17649" type="EtcItem" nameRu="Древняя Краска Ур. 2 - СИЛ" nameEn="Lv. 2 Ancient STR Dye">
		<!-- Древняя краска СИЛ Ур. 2 (СИЛ+4 ЛВК-3 Сопротивление огню +10). Если отдать 10 флаконов этой краски Мастеру Татуировок, то персонаж получит татуировку, изменяющую его характеристики. Требования: Все классы после перерождения и 3-го освобождения. -->
		<!-- Lv. 2 Ancient STR Dye (Str +4 Dex -3 Fire Resistance +10). Collect and take 10 units of this magical dye to the symbol maker in town and you will receive a symbol that boosts your abilities. Can be used after Awakening, or 3rd Liberation. All classes. -->
		<set name="icon" val="icon.lv2_2_dye_str" />
		<set name="weight" val="150" />
		<set name="price" val="1496100" />
		<set name="is_stackable" val="true" />
		<set name="etcitem_type" val="dye" />
		<set name="immediate_effect" val="1" />
		<!-- <set name="commissionItemType" val="DYES" \> -->
		<set name="material" val="liquid" />
	</item>
	<item id="17650" type="EtcItem" nameRu="Древняя Краска Ур. 2 - ЛВК" nameEn="Lv. 2 Ancient DEX Dye">
		<!-- Древняя краска ЛВК Ур. 2 (ЛВК+4 ВЫН-3 Сопротивление земле +10). Если отдать 10 флаконов этой краски Мастеру Татуировок, то персонаж получит татуировку, изменяющую его характеристики. Требования: Все классы после перерождения и 3-го освобождения. -->
		<!-- Lv. 2 Ancient DEX Dye (Dex +4 Con -3 Earth Resistance +10). Collect and take 10 units of this magical dye to the symbol maker in town and you will receive a symbol that boosts your abilities. Can be used after Awakening, or 3rd Liberation. All classes. -->
		<set name="icon" val="icon.lv2_2_dye_dex" />
		<set name="weight" val="150" />
		<set name="price" val="1496100" />
		<set name="is_stackable" val="true" />
		<set name="etcitem_type" val="dye" />
		<set name="immediate_effect" val="1" />
		<!-- <set name="commissionItemType" val="DYES" \> -->
		<set name="material" val="liquid" />
	</item>
	<item id="17651" type="EtcItem" nameRu="Древняя Краска Ур. 2 - ВЫН" nameEn="Lv. 2 Ancient CON Dye">
		<!-- Древняя краска ВЫН Ур. 2 (ВЫН+4 СИЛ-3 Сопротивление тьме +10). Если отдать 10 флаконов этой краски Мастеру Татуировок, то персонаж получит татуировку, изменяющую его характеристики. Требования: Все классы после перерождения и 3-го освобождения. -->
		<!-- Lv. 2 Ancient CON Dye (Con +4 Str -3 Dark Resistance +10). Collect and take 10 units of this magical dye to the symbol maker in town and you will receive a symbol that boosts your abilities. Can be used after Awakening, or 3rd Liberation. All classes. -->
		<set name="icon" val="icon.lv2_2_dye_con" />
		<set name="weight" val="150" />
		<set name="price" val="1496100" />
		<!-- <set name="commissionItemType" val="DYES" \> -->
		<set name="etcitem_type" val="dye" />
		<set name="immediate_effect" val="1" />
		<set name="is_stackable" val="true" />
		<set name="material" val="liquid" />
	</item>
	<item id="17652" type="EtcItem" nameRu="Древняя Краска Ур. 2 - ИНТ" nameEn="Lv. 2 Ancient INT Dye">
		<!-- Древняя краска ИНТ Ур. 2 (ИНТ+4 МДР-3 Сопротивление воде +10). Если отдать 10 флаконов этой краски Мастеру Татуировок, то персонаж получит татуировку, изменяющую его характеристики. Требования: Все классы после перерождения и 3-го освобождения. -->
		<!-- Lv. 2 Ancient INT Dye (Int +4 Wit -3 Water Resistance +10). Collect and take 10 units of this magical dye to the symbol maker in town and you will receive a symbol that boosts your abilities. Can be used after Awakening, or 3rd Liberation. All classes. -->
		<set name="icon" val="icon.lv2_2_dye_int" />
		<set name="weight" val="150" />
		<set name="price" val="1496100" />
		<set name="is_stackable" val="true" />
		<set name="etcitem_type" val="dye" />
		<set name="immediate_effect" val="1" />
		<!-- <set name="commissionItemType" val="DYES" \> -->
		<set name="material" val="liquid" />
	</item>
	<item id="17653" type="EtcItem" nameRu="Древняя Краска Ур. 2 - МДР" nameEn="Lv. 2 Ancient WIT Dye">
		<!-- Древняя краска МДР Ур. 2 (МДР+4 ДУХ-3 Сопротивление ветру +10). Если отдать 10 флаконов этой краски Мастеру Татуировок, то персонаж получит татуировку, изменяющую его характеристики. Требования: Все классы после перерождения и 3-го освобождения. -->
		<!-- Lv. 2 Ancient WIT Dye (Wit +4 Men -3 Wind Resistance +10). Collect and take 10 units of this magical dye to the symbol maker in town and you will receive a symbol that boosts your abilities. Can be used after Awakening, or 3rd Liberation. All classes. -->
		<set name="icon" val="icon.lv2_2_dye_wit" />
		<set name="weight" val="150" />
		<set name="price" val="1496100" />
		<set name="is_stackable" val="true" />
		<set name="etcitem_type" val="dye" />
		<set name="immediate_effect" val="1" />
		<!-- <set name="commissionItemType" val="DYES" \> -->
		<set name="material" val="liquid" />
	</item>
	<item id="17654" type="EtcItem" nameRu="Древняя Краска Ур. 2 - ДУХ" nameEn="Lv. 2 Ancient MEN Dye">
		<!-- Древняя краска ДУХ Ур. 2 (ДУХ+4 ИНТ-3 Сопротивление святости +10). Если отдать 10 флаконов этой краски Мастеру Татуировок, то персонаж получит татуировку, изменяющую его характеристики. Требования: Все классы после перерождения и 3-го освобождения. -->
		<!-- Lv. 2 Ancient MEN Dye (Men +4 Int -3 Holy Resistance +10). Collect and take 10 units of this magical dye to the symbol maker in town and you will receive a symbol that boosts your abilities. Can be used after Awakening, or 3rd Liberation. All classes. -->
		<set name="icon" val="icon.lv2_2_dye_men" />
		<set name="weight" val="150" />
		<set name="price" val="1496100" />
		<!-- <set name="commissionItemType" val="DYES" \> -->
		<set name="etcitem_type" val="dye" />
		<set name="immediate_effect" val="1" />
		<set name="is_stackable" val="true" />
		<set name="material" val="liquid" />
	</item>
	<item id="17655" type="EtcItem" nameRu="Легендарная Краска Ур. 2 - СИЛ" nameEn="Lv. 2 Legendary STR Dye">
		<!-- Легендарная краска СИЛ Ур. 2 (СИЛ+4 ЛВК-2 Сопротивление огню +10). Если отдать 10 флаконов этой краски Мастеру Татуировок, то персонаж получит татуировку, изменяющую его характеристики. Требования: Все классы после перерождения и 3-го освобождения. -->
		<!-- Lv. 2 Legendary STR Dye (Str +4 Dex -2 Fire Resistance +10). Collect and take 10 units of this magical dye to the symbol maker in town and you will receive a symbol that boosts your abilities. Can be used after Awakening, or 3rd Liberation. All classes. -->
		<set name="icon" val="icon.lv2_3_dye_str" />
		<set name="weight" val="150" />
		<set name="price" val="1894500" />
		<set name="is_stackable" val="true" />
		<set name="etcitem_type" val="dye" />
		<set name="immediate_effect" val="1" />
		<!-- <set name="commissionItemType" val="DYES" \> -->
		<set name="material" val="liquid" />
	</item>
	<item id="17656" type="EtcItem" nameRu="Легендарная Краска Ур. 2 - ЛВК" nameEn="Lv. 2 Legendary DEX Dye">
		<!-- Легендарная краска ЛВК Ур. 2 (ЛВК+4 ВЫН-2 Сопротивление земле +10). Если отдать 10 флаконов этой краски Мастеру Татуировок, то персонаж получит татуировку, изменяющую его характеристики. Требования: Все классы после перерождения и 3-го освобождения. -->
		<!-- Lv. 2 Legendary DEX Dye (Dex +4 Con -2 Earth Resistance +10). Collect and take 10 units of this magical dye to the symbol maker in town and you will receive a symbol that boosts your abilities. Can be used after Awakening, or 3rd Liberation. All classes. -->
		<set name="icon" val="icon.lv2_3_dye_dex" />
		<set name="weight" val="150" />
		<set name="price" val="1894500" />
		<set name="is_stackable" val="true" />
		<set name="etcitem_type" val="dye" />
		<set name="immediate_effect" val="1" />
		<!-- <set name="commissionItemType" val="DYES" \> -->
		<set name="material" val="liquid" />
	</item>
	<item id="17657" type="EtcItem" nameRu="Легендарная Краска Ур. 2 - ВЫН" nameEn="Lv. 2 Legendary CON Dye">
		<!-- Легендарная краска ВЫН Ур. 2 (ВЫН+4 СИЛ-2 Сопротивление тьме +10). Если отдать 10 флаконов этой краски Мастеру Татуировок, то персонаж получит татуировку, изменяющую его характеристики. Требования: Все классы после перерождения и 3-го освобождения. -->
		<!-- Lv. 2 Legendary CON Dye (Con +4 Str -2 Dark Resistance +10). Collect and take 10 units of this magical dye to the symbol maker in town and you will receive a symbol that boosts your abilities. Can be used after Awakening, or 3rd Liberation. All classes. -->
		<set name="icon" val="icon.lv2_3_dye_con" />
		<set name="weight" val="150" />
		<set name="price" val="1894500" />
		<set name="is_stackable" val="true" />
		<set name="etcitem_type" val="dye" />
		<set name="immediate_effect" val="1" />
		<!-- <set name="commissionItemType" val="DYES" \> -->
		<set name="material" val="liquid" />
	</item>
	<item id="17658" type="EtcItem" nameRu="Легендарная Краска Ур. 2 - ИНТ" nameEn="Lv. 2 Legendary INT Dye">
		<!-- Легендарная краска ИНТ Ур. 2 (ИНТ+4 МДР-2 Сопротивление воде +10). Если отдать 10 флаконов этой краски Мастеру Татуировок, то персонаж получит татуировку, изменяющую его характеристики. Требования: Все классы после перерождения и 3-го освобождения. -->
		<!-- Lv. 2 Legendary INT Dye (Int +4 Wit -2 Water Resistance +10). Collect and take 10 units of this magical dye to the symbol maker in town and you will receive a symbol that boosts your abilities. Can be used after Awakening, or 3rd Liberation. All classes. -->
		<set name="icon" val="icon.lv2_3_dye_int" />
		<set name="weight" val="150" />
		<set name="price" val="1894500" />
		<set name="is_stackable" val="true" />
		<set name="etcitem_type" val="dye" />
		<set name="immediate_effect" val="1" />
		<!-- <set name="commissionItemType" val="DYES" \> -->
		<set name="material" val="liquid" />
	</item>
	<item id="17659" type="EtcItem" nameRu="Легендарная Краска Ур. 2 - МДР" nameEn="Lv. 2 Legendary WIT Dye">
		<!-- Легендарная краска МДР Ур. 2 (МДР+4 ДУХ-2 Сопротивление ветру +10). Если отдать 10 флаконов этой краски Мастеру Татуировок, то персонаж получит татуировку, изменяющую его характеристики. Требования: Все классы после перерождения и 3-го освобождения. -->
		<!-- Lv. 2 Legendary WIT Dye (Wit +4 Men -2 Wind Resistance +10). Collect and take 10 units of this magical dye to the symbol maker in town and you will receive a symbol that boosts your abilities. Can be used after Awakening, or 3rd Liberation. All classes. -->
		<set name="icon" val="icon.lv2_3_dye_wit" />
		<set name="weight" val="150" />
		<set name="price" val="1894500" />
		<!-- <set name="commissionItemType" val="DYES" \> -->
		<set name="etcitem_type" val="dye" />
		<set name="immediate_effect" val="1" />
		<set name="is_stackable" val="true" />
		<set name="material" val="liquid" />
	</item>
	<item id="17660" type="EtcItem" nameRu="Легендарная Краска Ур. 2 - ДУХ" nameEn="Lv. 2 Legendary MEN Dye">
		<!-- Легендарная краска ДУХ Ур. 2 (ДУХ+4 ИНТ-2 Сопротивление святости +10). Если отдать 10 флаконов этой краски Мастеру Татуировок, то персонаж получит татуировку, изменяющую его характеристики. Требования: Все классы после перерождения и 3-го освобождения. -->
		<!-- Lv. 2 Legendary MEN Dye (Men +4 Int -2 Holy Resistance +10). Collect and take 10 units of this magical dye to the symbol maker in town and you will receive a symbol that boosts your abilities. Can be used after Awakening, or 3rd Liberation. All classes. -->
		<set name="icon" val="icon.lv2_3_dye_men" />
		<set name="weight" val="150" />
		<set name="price" val="1894500" />
		<!-- <set name="commissionItemType" val="DYES" \> -->
		<set name="etcitem_type" val="dye" />
		<set name="immediate_effect" val="1" />
		<set name="is_stackable" val="true" />
		<set name="material" val="liquid" />
	</item>
	<item id="17661" type="EtcItem" nameRu="Краска Гигантов Ур. 3 - СИЛ" nameEn="Lv. 3 Giant STR Dye">
		<!-- Краска СИЛ Гигантов Ур. 3 (СИЛ+5 ЛВК-4). Если отдать 10 флаконов этой краски Мастеру Татуировок, то персонаж получит татуировку, изменяющую его характеристики. Требования: Все классы после перерождения и 3-го освобождения. -->
		<!-- Lv. 3 Giant STR Dye (Str +5 Dex -4). Collect and take 10 units of this magical dye to the symbol maker in town and you will receive a symbol that boosts your abilities. Can be used after Awakening, or 3rd Liberation. All classes. -->
		<set name="icon" val="icon.lv3_1_dye_str" />
		<set name="weight" val="150" />
		<set name="price" val="2518000" />
		<!-- <set name="commissionItemType" val="DYES" \> -->
		<set name="etcitem_type" val="dye" />
		<set name="immediate_effect" val="1" />
		<set name="is_stackable" val="true" />
		<set name="material" val="liquid" />
	</item>
	<item id="17662" type="EtcItem" nameRu="Краска Гигантов Ур. 3 - ЛВК" nameEn="Lv. 3 Giant DEX Dye">
		<!-- Краска ЛВК Гигантов Ур. 3 (ЛВК+5 ВЫН-4). Если отдать 10 флаконов этой краски Мастеру Татуировок, то персонаж получит татуировку, изменяющую его характеристики. Требования: Все классы после перерождения и 3-го освобождения. -->
		<!-- Lv. 3 Giant DEX Dye (Dex +5 Con -4). Collect and take 10 units of this magical dye to the symbol maker in town and you will receive a symbol that boosts your abilities. Can be used after Awakening, or 3rd Liberation. All classes. -->
		<set name="icon" val="icon.lv3_1_dye_dex" />
		<set name="weight" val="150" />
		<set name="price" val="2518000" />
		<set name="is_stackable" val="true" />
		<set name="etcitem_type" val="dye" />
		<set name="immediate_effect" val="1" />
		<!-- <set name="commissionItemType" val="DYES" \> -->
		<set name="material" val="liquid" />
	</item>
	<item id="17663" type="EtcItem" nameRu="Краска Гигантов Ур. 3 - ВЫН" nameEn="Lv. 3 Giant CON Dye">
		<!-- Краска ВЫН Гигантов Ур. 3 (ВЫН+5 СИЛ-4). Если отдать 10 флаконов этой краски Мастеру Татуировок, то персонаж получит татуировку, изменяющую его характеристики. Требования: Все классы после перерождения и 3-го освобождения. -->
		<!-- Lv. 3 Giant CON Dye (Con +5 Str -4). Collect and take 10 units of this magical dye to the symbol maker in town and you will receive a symbol that boosts your abilities. Can be used after Awakening, or 3rd Liberation. All classes. -->
		<set name="icon" val="icon.lv3_1_dye_con" />
		<set name="weight" val="150" />
		<set name="price" val="2518000" />
		<set name="is_stackable" val="true" />
		<set name="etcitem_type" val="dye" />
		<set name="immediate_effect" val="1" />
		<!-- <set name="commissionItemType" val="DYES" \> -->
		<set name="material" val="liquid" />
	</item>
	<item id="17664" type="EtcItem" nameRu="Краска Гигантов Ур. 3 - ИНТ" nameEn="Lv. 3 Giant INT Dye">
		<!-- Краска ИНТ Гигантов Ур. 3 (ИНТ+5 МДР-4). Если отдать 10 флаконов этой краски Мастеру Татуировок, то персонаж получит татуировку, изменяющую его характеристики. Требования: Все классы после перерождения и 3-го освобождения. -->
		<!-- Lv. 3 Giant INT Dye (Int +5 Wit -4). Collect and take 10 units of this magical dye to the symbol maker in town and you will receive a symbol that boosts your abilities. Can be used after Awakening, or 3rd Liberation. All classes. -->
		<set name="icon" val="icon.lv3_1_dye_int" />
		<set name="weight" val="150" />
		<set name="price" val="2518000" />
		<set name="is_stackable" val="true" />
		<set name="etcitem_type" val="dye" />
		<set name="immediate_effect" val="1" />
		<!-- <set name="commissionItemType" val="DYES" \> -->
		<set name="material" val="liquid" />
	</item>
	<item id="17665" type="EtcItem" nameRu="Краска Гигантов Ур. 3 - МДР" nameEn="Lv. 3 Giant WIT Dye">
		<!-- Краска МДР Гигантов Ур. 3 (МДР+5 ДУХ-4). Если отдать 10 флаконов этой краски Мастеру Татуировок, то персонаж получит татуировку, изменяющую его характеристики. Требования: Все классы после перерождения и 3-го освобождения. -->
		<!-- Lv. 3 Giant WIT Dye (Wit +5 Men -4). Collect and take 10 units of this magical dye to the symbol maker in town and you will receive a symbol that boosts your abilities. Can be used after Awakening, or 3rd Liberation. All classes. -->
		<set name="icon" val="icon.lv3_1_dye_wit" />
		<set name="weight" val="150" />
		<set name="price" val="2518000" />
		<set name="is_stackable" val="true" />
		<set name="etcitem_type" val="dye" />
		<set name="immediate_effect" val="1" />
		<!-- <set name="commissionItemType" val="DYES" \> -->
		<set name="material" val="liquid" />
	</item>
	<item id="17666" type="EtcItem" nameRu="Краска Гигантов Ур. 3 - ДУХ" nameEn="Lv. 3 Giant MEN Dye">
		<!-- Краска ДУХ Гигантов Ур. 3 (ДУХ+5 ИНТ-4). Если отдать 10 флаконов этой краски Мастеру Татуировок, то персонаж получит татуировку, изменяющую его характеристики. Требования: Все классы после перерождения и 3-го освобождения. -->
		<!-- Lv. 3 Giant MEN Dye (Men +5 Int -4). Collect and take 10 units of this magical dye to the symbol maker in town and you will receive a symbol that boosts your abilities. Can be used after Awakening, or 3rd Liberation. All classes. -->
		<set name="icon" val="icon.lv3_1_dye_men" />
		<set name="weight" val="150" />
		<set name="price" val="2518000" />
		<!-- <set name="commissionItemType" val="DYES" \> -->
		<set name="etcitem_type" val="dye" />
		<set name="immediate_effect" val="1" />
		<set name="is_stackable" val="true" />
		<set name="material" val="liquid" />
	</item>
	<item id="17667" type="EtcItem" nameRu="Древняя Краска Ур. 3 - СИЛ" nameEn="Lv. 3 Ancient STR Dye">
		<!-- Древняя краска СИЛ Ур. 3 (СИЛ+5 ЛВК-4 Сопротивление огню +15). Если отдать 10 флаконов этой краски Мастеру Татуировок, то персонаж получит татуировку, изменяющую его характеристики. Требования: Все классы после перерождения и 3-го освобождения. -->
		<!-- Lv. 3 Ancient STR Dye (Str +5 Dex -4 Fire Resistance +15). Collect and take 10 units of this magical dye to the symbol maker in town and you will receive a symbol that boosts your abilities. Can be used after Awakening, or 3rd Liberation. All classes. -->
		<set name="icon" val="icon.lv3_2_dye_str" />
		<set name="weight" val="150" />
		<set name="price" val="3295800" />
		<!-- <set name="commissionItemType" val="DYES" \> -->
		<set name="etcitem_type" val="dye" />
		<set name="immediate_effect" val="1" />
		<set name="is_stackable" val="true" />
		<set name="material" val="liquid" />
	</item>
	<item id="17668" type="EtcItem" nameRu="Древняя Краска Ур. 3 - ЛВК" nameEn="Lv. 3 Ancient DEX Dye">
		<!-- Древняя краска ЛВК Ур. 3 (ЛВК+5 ВЫН-4 Сопротивление земле +15). Если отдать 10 флаконов этой краски Мастеру Татуировок, то персонаж получит татуировку, изменяющую его характеристики. Требования: Все классы после перерождения и 3-го освобождения. -->
		<!-- Lv. 3 Ancient DEX Dye (Dex +5 Con -4 Earth Resistance +15). Collect and take 10 units of this magical dye to the symbol maker in town and you will receive a symbol that boosts your abilities. Can be used after Awakening, or 3rd Liberation. All classes. -->
		<set name="icon" val="icon.lv3_2_dye_dex" />
		<set name="weight" val="150" />
		<set name="price" val="3295800" />
		<set name="is_stackable" val="true" />
		<set name="etcitem_type" val="dye" />
		<set name="immediate_effect" val="1" />
		<!-- <set name="commissionItemType" val="DYES" \> -->
		<set name="material" val="liquid" />
	</item>
	<item id="17669" type="EtcItem" nameRu="Древняя Краска Ур. 3 - ВЫН" nameEn="Lv. 3 Ancient CON Dye">
		<!-- Древняя краска ВЫН Ур. 3 (ВЫН+5 СИЛ-4 Сопротивление тьме +15). Если отдать 10 флаконов этой краски Мастеру Татуировок, то персонаж получит татуировку, изменяющую его характеристики. Требования: Все классы после перерождения и 3-го освобождения. -->
		<!-- Lv. 3 Ancient CON Dye (Con +5 Str -4 Dark Resistance +15). Collect and take 10 units of this magical dye to the symbol maker in town and you will receive a symbol that boosts your abilities. Can be used after Awakening, or 3rd Liberation. All classes. -->
		<set name="icon" val="icon.lv3_2_dye_con" />
		<set name="weight" val="150" />
		<set name="price" val="3295800" />
		<set name="is_stackable" val="true" />
		<set name="etcitem_type" val="dye" />
		<set name="immediate_effect" val="1" />
		<!-- <set name="commissionItemType" val="DYES" \> -->
		<set name="material" val="liquid" />
	</item>
	<item id="17670" type="EtcItem" nameRu="Древняя Краска Ур. 3 - ИНТ" nameEn="Lv. 3 Ancient INT Dye">
		<!-- Древняя краска ИНТ Ур. 3 (ИНТ+5 МДР-4 Сопротивление воде +15). Если отдать 10 флаконов этой краски Мастеру Татуировок, то персонаж получит татуировку, изменяющую его характеристики. Требования: Все классы после перерождения и 3-го освобождения. -->
		<!-- Lv. 3 Ancient INT Dye (Int +5 Wit -4 Water Resistance +15). Collect and take 10 units of this magical dye to the symbol maker in town and you will receive a symbol that boosts your abilities. Can be used after Awakening, or 3rd Liberation. All classes. -->
		<set name="icon" val="icon.lv3_2_dye_int" />
		<set name="weight" val="150" />
		<set name="price" val="3295800" />
		<set name="is_stackable" val="true" />
		<set name="etcitem_type" val="dye" />
		<set name="immediate_effect" val="1" />
		<!-- <set name="commissionItemType" val="DYES" \> -->
		<set name="material" val="liquid" />
	</item>
	<item id="17671" type="EtcItem" nameRu="Древняя Краска Ур. 3 - МДР" nameEn="Lv. 3 Ancient WIT Dye">
		<!-- Древняя краска МДР Ур. 3 (МДР+5 ДУХ-4 Сопротивление ветру +15). Если отдать 10 флаконов этой краски Мастеру Татуировок, то персонаж получит татуировку, изменяющую его характеристики. Требования: Все классы после перерождения и 3-го освобождения. -->
		<!-- Lv. 3 Ancient WIT Dye (Wit +5 Men -4 Wind Resistance +15). Collect and take 10 units of this magical dye to the symbol maker in town and you will receive a symbol that boosts your abilities. Can be used after Awakening, or 3rd Liberation. All classes. -->
		<set name="icon" val="icon.lv3_2_dye_wit" />
		<set name="weight" val="150" />
		<set name="price" val="3295800" />
		<set name="is_stackable" val="true" />
		<set name="etcitem_type" val="dye" />
		<set name="immediate_effect" val="1" />
		<!-- <set name="commissionItemType" val="DYES" \> -->
		<set name="material" val="liquid" />
	</item>
	<item id="17672" type="EtcItem" nameRu="Древняя Краска Ур. 3 - ДУХ" nameEn="Lv. 3 Ancient MEN Dye">
		<!-- Древняя краска ДУХ Ур. 3 (ДУХ+5 ИНТ-4 Сопротивление святости +15). Если отдать 10 флаконов этой краски Мастеру Татуировок, то персонаж получит татуировку, изменяющую его характеристики. Требования: Все классы после перерождения и 3-го освобождения. -->
		<!-- Lv. 3 Ancient MEN Dye (Men +5 Int -4 Holy Resistance +15). Collect and take 10 units of this magical dye to the symbol maker in town and you will receive a symbol that boosts your abilities. Can be used after Awakening, or 3rd Liberation. All classes. -->
		<set name="icon" val="icon.lv3_2_dye_men" />
		<set name="weight" val="150" />
		<set name="price" val="3295800" />
		<!-- <set name="commissionItemType" val="DYES" \> -->
		<set name="etcitem_type" val="dye" />
		<set name="immediate_effect" val="1" />
		<set name="is_stackable" val="true" />
		<set name="material" val="liquid" />
	</item>
	<item id="17673" type="EtcItem" nameRu="Легендарная Краска Ур. 3 - СИЛ" nameEn="Lv. 3 Legendary STR Dye">
		<!-- Легендарная краска СИЛ Ур. 3 (СИЛ+5 ЛВК-3 Сопротивление огню +15). Если отдать 10 флаконов этой краски Мастеру Татуировок, то персонаж получит татуировку, изменяющую его характеристики. Требования: Все классы после перерождения и 3-го освобождения. -->
		<!-- Lv. 3 Legendary STR Dye (Str +5 Dex -3 Fire Resistance +15). Collect and take 10 units of this magical dye to the symbol maker in town and you will receive a symbol that boosts your abilities. Can be used after Awakening, or 3rd Liberation. All classes. -->
		<set name="icon" val="icon.lv3_3_dye_str" />
		<set name="weight" val="150" />
		<set name="price" val="4073600" />
		<set name="is_stackable" val="true" />
		<set name="etcitem_type" val="dye" />
		<set name="immediate_effect" val="1" />
		<!-- <set name="commissionItemType" val="DYES" \> -->
		<set name="material" val="liquid" />
	</item>
	<item id="17674" type="EtcItem" nameRu="Легендарная Краска Ур. 3 - ЛВК" nameEn="Lv. 3 Legendary DEX Dye">
		<!-- Легендарная краска ЛВК Ур. 3 (ЛВК+5 ВЫН-3 Сопротивление земле +15). Если отдать 10 флаконов этой краски Мастеру Татуировок, то персонаж получит татуировку, изменяющую его характеристики. Требования: Все классы после перерождения и 3-го освобождения. -->
		<!-- Lv. 3 Legendary DEX Dye (Dex +5 Con -3 Earth Resistance +15). Collect and take 10 units of this magical dye to the symbol maker in town and you will receive a symbol that boosts your abilities. Can be used after Awakening, or 3rd Liberation. All classes. -->
		<set name="icon" val="icon.lv3_3_dye_dex" />
		<set name="weight" val="150" />
		<set name="price" val="4073600" />
		<set name="is_stackable" val="true" />
		<set name="etcitem_type" val="dye" />
		<set name="immediate_effect" val="1" />
		<!-- <set name="commissionItemType" val="DYES" \> -->
		<set name="material" val="liquid" />
	</item>
	<item id="17675" type="EtcItem" nameRu="Легендарная Краска Ур. 3 - ВЫН" nameEn="Lv. 3 Legendary CON Dye">
		<!-- Легендарная краска ВЫН Ур. 3 (ВЫН+5 СИЛ-3 Сопротивление тьме +15). Если отдать 10 флаконов этой краски Мастеру Татуировок, то персонаж получит татуировку, изменяющую его характеристики. Требования: Все классы после перерождения и 3-го освобождения. -->
		<!-- Lv. 3 Legendary CON Dye (Con +5 Str -3 Dark Resistance +15). Collect and take 10 units of this magical dye to the symbol maker in town and you will receive a symbol that boosts your abilities. Can be used after Awakening, or 3rd Liberation. All classes. -->
		<set name="icon" val="icon.lv3_3_dye_con" />
		<set name="weight" val="150" />
		<set name="price" val="4073600" />
		<set name="is_stackable" val="true" />
		<set name="etcitem_type" val="dye" />
		<set name="immediate_effect" val="1" />
		<!-- <set name="commissionItemType" val="DYES" \> -->
		<set name="material" val="liquid" />
	</item>
	<item id="17676" type="EtcItem" nameRu="Легендарная Краска Ур. 3 - ИНТ" nameEn="Lv. 3 Legendary INT Dye">
		<!-- Легендарная краска ИНТ Ур. 3 (ИНТ+5 МДР-3 Сопротивление воде +15). Если отдать 10 флаконов этой краски Мастеру Татуировок, то персонаж получит татуировку, изменяющую его характеристики. Требования: Все классы после перерождения и 3-го освобождения. -->
		<!-- Lv. 3 Legendary INT Dye (Int +5 Wit -3 Water Resistance +15). Collect and take 10 units of this magical dye to the symbol maker in town and you will receive a symbol that boosts your abilities. Can be used after Awakening, or 3rd Liberation. All classes. -->
		<set name="icon" val="icon.lv3_3_dye_int" />
		<set name="weight" val="150" />
		<set name="price" val="4073600" />
		<set name="is_stackable" val="true" />
		<set name="etcitem_type" val="dye" />
		<set name="immediate_effect" val="1" />
		<!-- <set name="commissionItemType" val="DYES" \> -->
		<set name="material" val="liquid" />
	</item>
	<item id="17677" type="EtcItem" nameRu="Легендарная Краска Ур. 3 - МДР" nameEn="Lv. 3 Legendary WIT Dye">
		<!-- Легендарная краска МДР Ур. 3 (МДР+5 ДУХ-3 Сопротивление ветру +15). Если отдать 10 флаконов этой краски Мастеру Татуировок, то персонаж получит татуировку, изменяющую его характеристики. Требования: Все классы после перерождения и 3-го освобождения. -->
		<!-- Lv. 3 Legendary WIT Dye (Wit +5 Men -3 Wind Resistance +15). Collect and take 10 units of this magical dye to the symbol maker in town and you will receive a symbol that boosts your abilities. Can be used after Awakening, or 3rd Liberation. All classes. -->
		<set name="icon" val="icon.lv3_3_dye_wit" />
		<set name="weight" val="150" />
		<set name="price" val="4073600" />
		<set name="is_stackable" val="true" />
		<set name="etcitem_type" val="dye" />
		<set name="immediate_effect" val="1" />
		<!-- <set name="commissionItemType" val="DYES" \> -->
		<set name="material" val="liquid" />
	</item>
	<item id="17678" type="EtcItem" nameRu="Легендарная Краска Ур. 3 - ДУХ" nameEn="Lv. 3 Legendary MEN Dye">
		<!-- Легендарная краска ДУХ Ур. 3 (ДУХ+5 ИНТ-3 Сопротивление святости +15). Если отдать 10 флаконов этой краски Мастеру Татуировок, то персонаж получит татуировку, изменяющую его характеристики. Требования: Все классы после перерождения и 3-го освобождения. -->
		<!-- Lv. 3 Legendary MEN Dye (Men +5 Int -3 Holy Resistance +15). Collect and take 10 units of this magical dye to the symbol maker in town and you will receive a symbol that boosts your abilities. Can be used after Awakening, or 3rd Liberation. All classes. -->
		<set name="icon" val="icon.lv3_3_dye_men" />
		<set name="weight" val="150" />
		<set name="price" val="4073600" />
		<set name="is_stackable" val="true" />
		<set name="etcitem_type" val="dye" />
		<set name="immediate_effect" val="1" />
		<!-- <set name="commissionItemType" val="DYES" \> -->
		<set name="material" val="liquid" />
	</item>
	<item id="17679" type="EtcItem" nameRu="Краска Гигантов Ур. 4 - СИЛ" nameEn="Lv. 4 Giant STR Dye">
		<!-- Краска СИЛ Гигантов Ур. 4 (СИЛ+5 ЛВК-2). Если отдать 10 флаконов этой краски Мастеру Татуировок, то персонаж получит татуировку, изменяющую его характеристики. Требования: Все классы после перерождения и 3-го освобождения. -->
		<!-- Lv. 4 Giant STR Dye (Str +5 Dex -2). Collect and take 10 units of this magical dye to the symbol maker in town and you will receive a symbol that boosts your abilities. Can be used after Awakening, or 3rd Liberation. All classes. -->
		<set name="icon" val="icon.lv4_1_dye_str" />
		<set name="weight" val="150" />
		<set name="price" val="11334400" />
		<set name="is_stackable" val="true" />
		<set name="etcitem_type" val="dye" />
		<set name="immediate_effect" val="1" />
		<!-- <set name="commissionItemType" val="DYES" \> -->
		<set name="material" val="liquid" />
	</item>
	<item id="17680" type="EtcItem" nameRu="Краска Гигантов Ур. 4 - ЛВК" nameEn="Lv. 4 Giant DEX Dye">
		<!-- Краска ЛВК Гигантов Ур. 4 (ЛВК+5 ВЫН-2). Если отдать 10 флаконов этой краски Мастеру Татуировок, то персонаж получит татуировку, изменяющую его характеристики. Требования: Все классы после перерождения и 3-го освобождения. -->
		<!-- Lv. 4 Giant DEX Dye (Dex +5 Con -2). Collect and take 10 units of this magical dye to the symbol maker in town and you will receive a symbol that boosts your abilities. Can be used after Awakening, or 3rd Liberation. All classes. -->
		<set name="icon" val="icon.lv4_1_dye_dex" />
		<set name="weight" val="150" />
		<set name="price" val="11334400" />
		<set name="is_stackable" val="true" />
		<set name="etcitem_type" val="dye" />
		<set name="immediate_effect" val="1" />
		<!-- <set name="commissionItemType" val="DYES" \> -->
		<set name="material" val="liquid" />
	</item>
	<item id="17681" type="EtcItem" nameRu="Краска Гигантов Ур. 4 - ВЫН" nameEn="Lv. 4 Giant CON Dye">
		<!-- Краска ВЫН Гигантов Ур. 4 (ВЫН+5 СИЛ-2). Если отдать 10 флаконов этой краски Мастеру Татуировок, то персонаж получит татуировку, изменяющую его характеристики. Требования: Все классы после перерождения и 3-го освобождения. -->
		<!-- Lv. 4 Giant CON Dye (Con +5 Str -2). Collect and take 10 units of this magical dye to the symbol maker in town and you will receive a symbol that boosts your abilities. Can be used after Awakening, or 3rd Liberation. All classes. -->
		<set name="icon" val="icon.lv4_1_dye_con" />
		<set name="weight" val="150" />
		<set name="price" val="11334400" />
		<set name="is_stackable" val="true" />
		<set name="etcitem_type" val="dye" />
		<set name="immediate_effect" val="1" />
		<!-- <set name="commissionItemType" val="DYES" \> -->
		<set name="material" val="liquid" />
	</item>
	<item id="17682" type="EtcItem" nameRu="Краска Гигантов Ур. 4 - ИНТ" nameEn="Lv. 4 Giant INT Dye">
		<!-- Краска ИНТ Гигантов Ур. 4 (ИНТ+5 МДР-2). Если отдать 10 флаконов этой краски Мастеру Татуировок, то персонаж получит татуировку, изменяющую его характеристики. Требования: Все классы после перерождения и 3-го освобождения. -->
		<!-- Lv. 4 Giant INT Dye (Int +5 Wit -2). Collect and take 10 units of this magical dye to the symbol maker in town and you will receive a symbol that boosts your abilities. Can be used after Awakening, or 3rd Liberation. All classes. -->
		<set name="icon" val="icon.lv4_1_dye_int" />
		<set name="weight" val="150" />
		<set name="price" val="11334400" />
		<set name="is_stackable" val="true" />
		<set name="etcitem_type" val="dye" />
		<set name="immediate_effect" val="1" />
		<!-- <set name="commissionItemType" val="DYES" \> -->
		<set name="material" val="liquid" />
	</item>
	<item id="17683" type="EtcItem" nameRu="Краска Гигантов Ур. 4 - МДР" nameEn="Lv. 4 Giant WIT Dye">
		<!-- Краска МДР Гигантов Ур. 4 (МДР+5 ДУХ-2). Если отдать 10 флаконов этой краски Мастеру Татуировок, то персонаж получит татуировку, изменяющую его характеристики. Требования: Все классы после перерождения и 3-го освобождения. -->
		<!-- Lv. 4 Giant WIT Dye (Wit +5 Men -2). Collect and take 10 units of this magical dye to the symbol maker in town and you will receive a symbol that boosts your abilities. Can be used after Awakening, or 3rd Liberation. All classes. -->
		<set name="icon" val="icon.lv4_1_dye_wit" />
		<set name="weight" val="150" />
		<set name="price" val="11334400" />
		<set name="is_stackable" val="true" />
		<set name="etcitem_type" val="dye" />
		<set name="immediate_effect" val="1" />
		<!-- <set name="commissionItemType" val="DYES" \> -->
		<set name="material" val="liquid" />
	</item>
	<item id="17684" type="EtcItem" nameRu="Краска Гигантов Ур. 4 - ДУХ" nameEn="Lv. 4 Giant MEN Dye">
		<!-- Краска ДУХ Гигантов Ур. 4 (ДУХ+5 ИНТ-2). Если отдать 10 флаконов этой краски Мастеру Татуировок, то персонаж получит татуировку, изменяющую его характеристики. Требования: Все классы после перерождения и 3-го освобождения. -->
		<!-- Lv. 4 Giant MEN Dye (Men +5 Int -2). Collect and take 10 units of this magical dye to the symbol maker in town and you will receive a symbol that boosts your abilities. Can be used after Awakening, or 3rd Liberation. All classes. -->
		<set name="icon" val="icon.lv4_1_dye_men" />
		<set name="weight" val="150" />
		<set name="price" val="11334400" />
		<set name="is_stackable" val="true" />
		<set name="etcitem_type" val="dye" />
		<set name="immediate_effect" val="1" />
		<!-- <set name="commissionItemType" val="DYES" \> -->
		<set name="material" val="liquid" />
	</item>
	<item id="17685" type="EtcItem" nameRu="Древняя Краска Ур. 4 - СИЛ" nameEn="Lv. 4 Ancient STR Dye">
		<!-- Древняя краска СИЛ Ур. 4 (СИЛ+5 ЛВК-2 Сопротивление огню +20). Если отдать 10 флаконов этой краски Мастеру Татуировок, то персонаж получит татуировку, изменяющую его характеристики. Требования: Все классы после перерождения и 3-го освобождения. -->
		<!-- Lv. 4 Ancient STR Dye (Str +5 Dex -2 Fire Resistance +20). Collect and take 10 units of this magical dye to the symbol maker in town and you will receive a symbol that boosts your abilities. Can be used after Awakening, or 3rd Liberation. All classes. -->
		<set name="icon" val="icon.lv4_2_dye_str" />
		<set name="weight" val="150" />
		<set name="price" val="12966700" />
		<set name="is_stackable" val="true" />
		<set name="etcitem_type" val="dye" />
		<set name="immediate_effect" val="1" />
		<!-- <set name="commissionItemType" val="DYES" \> -->
		<set name="material" val="liquid" />
	</item>
	<item id="17686" type="EtcItem" nameRu="Древняя Краска Ур. 4 - ЛВК" nameEn="Lv. 4 Ancient DEX Dye">
		<!-- Древняя краска ЛВК Ур. 4 (ЛВК+5 ВЫН-2 Сопротивление земле +20). Если отдать 10 флаконов этой краски Мастеру Татуировок, то персонаж получит татуировку, изменяющую его характеристики. Требования: Все классы после перерождения и 3-го освобождения. -->
		<!-- Lv. 4 Ancient DEX Dye (Dex +5 Con -2 Earth Resistance +20). Collect and take 10 units of this magical dye to the symbol maker in town and you will receive a symbol that boosts your abilities. Can be used after Awakening, or 3rd Liberation. All classes. -->
		<set name="icon" val="icon.lv4_2_dye_dex" />
		<set name="weight" val="150" />
		<set name="price" val="12966700" />
		<set name="is_stackable" val="true" />
		<set name="etcitem_type" val="dye" />
		<set name="immediate_effect" val="1" />
		<!-- <set name="commissionItemType" val="DYES" \> -->
		<set name="material" val="liquid" />
	</item>
	<item id="17687" type="EtcItem" nameRu="Древняя Краска Ур. 4 - ВЫН" nameEn="Lv. 4 Ancient CON Dye">
		<!-- Древняя краска ВЫН Ур. 4 (ВЫН+5 СИЛ-2 Сопротивление тьме +20). Если отдать 10 флаконов этой краски Мастеру Татуировок, то персонаж получит татуировку, изменяющую его характеристики. Требования: Все классы после перерождения и 3-го освобождения. -->
		<!-- Lv. 4 Ancient CON Dye (Con +5 Str -2 Dark Resistance +20). Collect and take 10 units of this magical dye to the symbol maker in town and you will receive a symbol that boosts your abilities. Can be used after Awakening, or 3rd Liberation. All classes. -->
		<set name="icon" val="icon.lv4_2_dye_con" />
		<set name="weight" val="150" />
		<set name="price" val="12966700" />
		<set name="is_stackable" val="true" />
		<set name="etcitem_type" val="dye" />
		<set name="immediate_effect" val="1" />
		<!-- <set name="commissionItemType" val="DYES" \> -->
		<set name="material" val="liquid" />
	</item>
	<item id="17688" type="EtcItem" nameRu="Древняя Краска Ур. 4 - ИНТ" nameEn="Lv. 4 Ancient INT Dye">
		<!-- Древняя краска ИНТ Ур. 4 (ИНТ+5 МДР-2 Сопротивление воде +20). Если отдать 10 флаконов этой краски Мастеру Татуировок, то персонаж получит татуировку, изменяющую его характеристики. Требования: Все классы после перерождения и 3-го освобождения. -->
		<!-- Lv. 4 Ancient INT Dye (Int +5 Wit -2 Water Resistance +20). Collect and take 10 units of this magical dye to the symbol maker in town and you will receive a symbol that boosts your abilities. Can be used after Awakening, or 3rd Liberation. All classes. -->
		<set name="icon" val="icon.lv4_2_dye_int" />
		<set name="weight" val="150" />
		<set name="price" val="12966700" />
		<set name="is_stackable" val="true" />
		<set name="etcitem_type" val="dye" />
		<set name="immediate_effect" val="1" />
		<!-- <set name="commissionItemType" val="DYES" \> -->
		<set name="material" val="liquid" />
	</item>
	<item id="17689" type="EtcItem" nameRu="Древняя Краска Ур. 4 - МДР" nameEn="Lv. 4 Ancient WIT Dye">
		<!-- Древняя краска МДР Ур. 4 (МДР+5 ДУХ-2 Сопротивление ветру +20). Если отдать 10 флаконов этой краски Мастеру Татуировок, то персонаж получит татуировку, изменяющую его характеристики. Требования: Все классы после перерождения и 3-го освобождения. -->
		<!-- Lv. 4 Ancient WIT Dye (Wit +5 Men -2 Wind Resistance +20). Collect and take 10 units of this magical dye to the symbol maker in town and you will receive a symbol that boosts your abilities. Can be used after Awakening, or 3rd Liberation. All classes. -->
		<set name="icon" val="icon.lv4_2_dye_wit" />
		<set name="weight" val="150" />
		<set name="price" val="12966700" />
		<!-- <set name="commissionItemType" val="DYES" \> -->
		<set name="etcitem_type" val="dye" />
		<set name="immediate_effect" val="1" />
		<set name="is_stackable" val="true" />
		<set name="material" val="liquid" />
	</item>
	<item id="17690" type="EtcItem" nameRu="Древняя Краска Ур. 4 - ДУХ" nameEn="Lv. 4 Ancient MEN Dye">
		<!-- Древняя краска ДУХ Ур. 4 (ДУХ+5 ИНТ-2 Сопротивление святости +20). Если отдать 10 флаконов этой краски Мастеру Татуировок, то персонаж получит татуировку, изменяющую его характеристики. Требования: Все классы после перерождения и 3-го освобождения. -->
		<!-- Lv. 4 Ancient MEN Dye (Men +5 Int -2 Holy Resistance +20). Collect and take 10 units of this magical dye to the symbol maker in town and you will receive a symbol that boosts your abilities. Can be used after Awakening, or 3rd Liberation. All classes. -->
		<set name="icon" val="icon.lv4_2_dye_men" />
		<set name="weight" val="150" />
		<set name="price" val="12966700" />
		<set name="is_stackable" val="true" />
		<set name="etcitem_type" val="dye" />
		<set name="immediate_effect" val="1" />
		<!-- <set name="commissionItemType" val="DYES" \> -->
		<set name="material" val="liquid" />
	</item>
	<item id="17691" type="EtcItem" nameRu="Легендарная Краска Ур. 4 - СИЛ" nameEn="Lv. 4 Legendary STR Dye">
		<!-- Легендарная краска СИЛ Ур. 4 (СИЛ+5 ЛВК-1 Сопротивление огню +20). Если отдать 10 флаконов этой краски Мастеру Татуировок, то персонаж получит татуировку, изменяющую его характеристики. Требования: Все классы после перерождения и 3-го освобождения. -->
		<!-- Lv. 4 Legendary STR Dye (Str +5 Dex -1 Fire Resistance +20). Collect and take 10 units of this magical dye to the symbol maker in town and you will receive a symbol that boosts your abilities. Can be used after Awakening, or 3rd Liberation. All classes. -->
		<set name="icon" val="icon.lv4_3_dye_str" />
		<set name="weight" val="150" />
		<set name="price" val="14598900" />
		<set name="is_stackable" val="true" />
		<set name="etcitem_type" val="dye" />
		<set name="immediate_effect" val="1" />
		<!-- <set name="commissionItemType" val="DYES" \> -->
		<set name="material" val="liquid" />
	</item>
	<item id="17692" type="EtcItem" nameRu="Легендарная Краска Ур. 4 - ЛВК" nameEn="Lv. 4 Legendary DEX Dye">
		<!-- Легендарная краска ЛВК Ур. 4 (ЛВК+5 ВЫН-1 Сопротивление земле +20). Если отдать 10 флаконов этой краски Мастеру Татуировок, то персонаж получит татуировку, изменяющую его характеристики. Требования: Все классы после перерождения и 3-го освобождения. -->
		<!-- Lv. 4 Legendary DEX Dye (Dex +5 Con -1 Earth Resistance +20). Collect and take 10 units of this magical dye to the symbol maker in town and you will receive a symbol that boosts your abilities. Can be used after Awakening, or 3rd Liberation. All classes. -->
		<set name="icon" val="icon.lv4_3_dye_dex" />
		<set name="weight" val="150" />
		<set name="price" val="14598900" />
		<set name="is_stackable" val="true" />
		<set name="etcitem_type" val="dye" />
		<set name="immediate_effect" val="1" />
		<!-- <set name="commissionItemType" val="DYES" \> -->
		<set name="material" val="liquid" />
	</item>
	<item id="17693" type="EtcItem" nameRu="Легендарная Краска Ур. 4 - ВЫН" nameEn="Lv. 4 Legendary CON Dye">
		<!-- Легендарная краска ВЫН Ур. 4 (ВЫН+5 СИЛ-1 Сопротивление тьме +20). Если отдать 10 флаконов этой краски Мастеру Татуировок, то персонаж получит татуировку, изменяющую его характеристики. Требования: Все классы после перерождения и 3-го освобождения. -->
		<!-- Lv. 4 Legendary CON Dye (Con +5 Str -1 Dark Resistance +20). Collect and take 10 units of this magical dye to the symbol maker in town and you will receive a symbol that boosts your abilities. Can be used after Awakening, or 3rd Liberation. All classes. -->
		<set name="icon" val="icon.lv4_3_dye_con" />
		<set name="weight" val="150" />
		<set name="price" val="14598900" />
		<set name="is_stackable" val="true" />
		<set name="etcitem_type" val="dye" />
		<set name="immediate_effect" val="1" />
		<!-- <set name="commissionItemType" val="DYES" \> -->
		<set name="material" val="liquid" />
	</item>
	<item id="17694" type="EtcItem" nameRu="Легендарная Краска Ур. 4 - ИНТ" nameEn="Lv. 4 Legendary INT Dye">
		<!-- Легендарная краска ИНТ Ур. 4 (ИНТ+5 МДР-1 Сопротивление воде +20). Если отдать 10 флаконов этой краски Мастеру Татуировок, то персонаж получит татуировку, изменяющую его характеристики. Требования: Все классы после перерождения и 3-го освобождения. -->
		<!-- Lv. 4 Legendary INT Dye (Int +5 Wit -1 Water Resistance +20). Collect and take 10 units of this magical dye to the symbol maker in town and you will receive a symbol that boosts your abilities. Can be used after Awakening, or 3rd Liberation. All classes. -->
		<set name="icon" val="icon.lv4_3_dye_int" />
		<set name="weight" val="150" />
		<set name="price" val="14598900" />
		<set name="is_stackable" val="true" />
		<set name="etcitem_type" val="dye" />
		<set name="immediate_effect" val="1" />
		<!-- <set name="commissionItemType" val="DYES" \> -->
		<set name="material" val="liquid" />
	</item>
	<item id="17695" type="EtcItem" nameRu="Легендарная Краска Ур. 4 - МДР" nameEn="Lv. 4 Legendary WIT Dye">
		<!-- Легендарная краска МДР Ур. 4 (МДР+5 ДУХ-1 Сопротивление ветру +20). Если отдать 10 флаконов этой краски Мастеру Татуировок, то персонаж получит татуировку, изменяющую его характеристики. Требования: Все классы после перерождения и 3-го освобождения. -->
		<!-- Lv. 4 Legendary WIT Dye (Wit +5 Men -1 Wind Resistance +20). Collect and take 10 units of this magical dye to the symbol maker in town and you will receive a symbol that boosts your abilities. Can be used after Awakening, or 3rd Liberation. All classes. -->
		<set name="icon" val="icon.lv4_3_dye_wit" />
		<set name="weight" val="150" />
		<set name="price" val="14598900" />
		<set name="is_stackable" val="true" />
		<set name="etcitem_type" val="dye" />
		<set name="immediate_effect" val="1" />
		<!-- <set name="commissionItemType" val="DYES" \> -->
		<set name="material" val="liquid" />
	</item>
	<item id="17696" type="EtcItem" nameRu="Легендарная Краска Ур. 4 - ДУХ" nameEn="Lv. 4 Legendary MEN Dye">
		<!-- Легендарная краска ДУХ Ур. 4 (ДУХ+5 ИНТ-1 Сопротивление святости +20). Если отдать 10 флаконов этой краски Мастеру Татуировок, то персонаж получит татуировку, изменяющую его характеристики. Требования: Все классы после перерождения и 3-го освобождения. -->
		<!-- Lv. 4 Legendary MEN Dye (Men +5 Int -1 Holy Resistance +20). Collect and take 10 units of this magical dye to the symbol maker in town and you will receive a symbol that boosts your abilities. Can be used after Awakening, or 3rd Liberation. All classes. -->
		<set name="icon" val="icon.lv4_3_dye_men" />
		<set name="weight" val="150" />
		<set name="price" val="14598900" />
		<!-- <set name="commissionItemType" val="DYES" \> -->
		<set name="etcitem_type" val="dye" />
		<set name="immediate_effect" val="1" />
		<set name="is_stackable" val="true" />
		<set name="material" val="liquid" />
	</item>
	<item id="17697" type="EtcItem" nameRu="Краска Гигантов Ур. 5 - СИЛ" nameEn="Lv. 5 Giant STR Dye">
		<!-- Краска СИЛ Гигантов Ур. 5 (СИЛ+5). Если отдать 10 флаконов этой краски Мастеру Татуировок, то персонаж получит татуировку, изменяющую его характеристики. Требования: Все классы после перерождения и 3-го освобождения. -->
		<!-- Lv. 5 Giant STR Dye (Str +5). Collect and take 10 units of this magical dye to the symbol maker in town and you will receive a symbol that boosts your abilities. Can be used after Awakening, or 3rd Liberation. All classes. -->
		<set name="icon" val="icon.lv5_1_dye_str" />
		<set name="weight" val="150" />
		<set name="price" val="35884300" />
		<set name="is_stackable" val="true" />
		<set name="etcitem_type" val="dye" />
		<set name="immediate_effect" val="1" />
		<!-- <set name="commissionItemType" val="DYES" \> -->
		<set name="material" val="liquid" />
	</item>
	<item id="17698" type="EtcItem" nameRu="Краска Гигантов Ур. 5 - ЛВК" nameEn="Lv. 5 Giant DEX Dye">
		<!-- Краска ЛВК Гигантов Ур. 5 (ЛВК+5). Если отдать 10 флаконов этой краски Мастеру Татуировок, то персонаж получит татуировку, изменяющую его характеристики. Требования: Все классы после перерождения и 3-го освобождения. -->
		<!-- Lv. 5 Giant DEX Dye (Dex +5). Collect and take 10 units of this magical dye to the symbol maker in town and you will receive a symbol that boosts your abilities. Can be used after Awakening, or 3rd Liberation. All classes. -->
		<set name="icon" val="icon.lv5_1_dye_dex" />
		<set name="weight" val="150" />
		<set name="price" val="35884300" />
		<set name="is_stackable" val="true" />
		<set name="etcitem_type" val="dye" />
		<set name="immediate_effect" val="1" />
		<!-- <set name="commissionItemType" val="DYES" \> -->
		<set name="material" val="liquid" />
	</item>
	<item id="17699" type="EtcItem" nameRu="Краска Гигантов Ур. 5 - ВЫН" nameEn="Lv. 5 Giant CON Dye">
		<!-- Краска ВЫН Гигантов Ур. 5 (ВЫН+5). Если отдать 10 флаконов этой краски Мастеру Татуировок, то персонаж получит татуировку, изменяющую его характеристики. Требования: Все классы после перерождения и 3-го освобождения. -->
		<!-- Lv. 5 Giant CON Dye (Con +5). Collect and take 10 units of this magical dye to the symbol maker in town and you will receive a symbol that boosts your abilities. Can be used after Awakening, or 3rd Liberation. All classes. -->
		<set name="icon" val="icon.lv5_1_dye_con" />
		<set name="weight" val="150" />
		<set name="price" val="35884300" />
		<set name="is_stackable" val="true" />
		<set name="etcitem_type" val="dye" />
		<set name="immediate_effect" val="1" />
		<!-- <set name="commissionItemType" val="DYES" \> -->
		<set name="material" val="liquid" />
	</item>
</list>