<?xml version="1.0" encoding="UTF-8"?>
<list xmlns:xsi="http://www.w3.org/2001/XMLSchema-instance" xsi:noNamespaceSchemaLocation="../../xsd/items.xsd">
	<item id="46100" type="EtcItem" nameRu="Карта Сокровищ Верховного Жреца Раймонда" nameEn="Treasure Map - High Priest Raymond">
		<!-- Карта с указанием места, где спрятаны сокровища. Текст на карте очень плохо сохранился. Но несмотря на это, можно разглядеть надпись "верховный жрец"... Похоже это были сокровища в дар храму. -->
		<!-- A map showing the location of some treasure. It says "For the High Priest", so it's probably a gift for the temple. -->
		<set name="icon" val="icon.etc_map_yellow_i04" />
		<set name="is_depositable" val="false" />
		<set name="is_tradable" val="false" />
		<set name="is_dropable" val="false" />
		<set name="is_sellable" val="false" />
		<set name="is_stackable" val="true" />
		<set name="material" val="leather" />
	</item>
	<item id="46101" type="EtcItem" nameRu="Карта Сокровищ Наследия Орков Турек" nameEn="Treasure Map - Turek Orc's Legacy">
		<!-- Карта с указанием места, где спрятаны сокровища. На ней написано "Слава Оркам Турек". Похоже эти сокровища принадлежали именно им. -->
		<!-- A map showing the location of some treasure. It says, "Glory to the Turek Orcs". It looks like it is related to the Turek Orcs. -->
		<set name="icon" val="icon.etc_map_yellow_i05" />
		<set name="is_depositable" val="false" />
		<set name="is_tradable" val="false" />
		<set name="is_dropable" val="false" />
		<set name="is_sellable" val="false" />
		<set name="is_stackable" val="true" />
		<set name="material" val="leather" />
	</item>
	<item id="46102" type="EtcItem" nameRu="Сундук с Сокровищами Закена" nameEn="Zaken's Treasure Chest">
		<!-- По двойному щелчку персонаж получит предмет, который ему пригодится. -->
		<!-- Zaken's treasure chest. Double-click to get an item. -->
		<set name="icon" val="icon.etc_jewel_box_i00" />
		<set name="is_sellable" val="false" />
		<set name="is_stackable" val="true" />
		<set name="material" val="paper" />
	</item>
	<item id="46103" type="EtcItem" nameRu="Сундук с Сокровищами Леоны Блэкберд" nameEn="Leona Blackbird's Treasure Chest">
		<!-- По двойному щелчку персонаж получит предмет, который ему пригодится. -->
		<!-- Leona Blackbird's treasure chest. Double-click to get an item. -->
		<set name="icon" val="icon.etc_jewel_box_i00" />
		<set name="is_sellable" val="false" />
		<set name="is_stackable" val="true" />
		<set name="material" val="paper" />
	</item>
	<item id="46104" type="EtcItem" nameRu="Сундук с Сокровищами Беоры" nameEn="Beora's Treasure Chest">
		<!-- По двойному щелчку персонаж получит предмет, который ему пригодится. -->
		<!-- Beora's treasure chest. Double-click to get an item. -->
		<set name="icon" val="icon.etc_jewel_box_i00" />
		<set name="is_sellable" val="false" />
		<set name="is_stackable" val="true" />
		<set name="material" val="paper" />
	</item>
	<item id="46105" type="EtcItem" nameRu="Сундук с Сокровищами Гладиатора" nameEn="Gladiator's Treasure Chest">
		<!-- По двойному щелчку персонаж получит предмет, который ему пригодится. -->
		<!-- Gladiator's treasure chest. Double-click to get an item. -->
		<set name="icon" val="icon.etc_jewel_box_i00" />
		<set name="is_sellable" val="false" />
		<set name="is_stackable" val="true" />
		<set name="material" val="paper" />
	</item>
	<item id="46106" type="EtcItem" nameRu="Сундук с Сокровищами Раймонда" nameEn="Raymond's Treasure Chest">
		<!-- По двойному щелчку персонаж получит предмет, который ему пригодится. -->
		<!-- Raymond's treasure chest. Double-click to get an item. -->
		<set name="icon" val="icon.etc_jewel_box_i00" />
		<set name="is_sellable" val="false" />
		<set name="is_stackable" val="true" />
		<set name="material" val="paper" />
	</item>
	<item id="46107" type="EtcItem" nameRu="Сундук с Сокровищами Орков Турек" nameEn="Turek Orc's Treasure Chest">
		<!-- По двойному щелчку персонаж получит предмет, который ему пригодится. -->
		<!-- Turek Orc's treasure chest. Double-click to get an item. -->
		<set name="icon" val="icon.etc_jewel_box_i00" />
		<set name="is_sellable" val="false" />
		<set name="is_stackable" val="true" />
		<set name="material" val="paper" />
	</item>
	<item id="46108" type="EtcItem" nameRu="Камень Обработки Булавы Дрейка" nameEn="Drake Maul Appearance Stone">
		<!-- Позволяет на 30 д. придать двуручному дробящему оружию вид Булавы Дрейка. -->
		<!-- Changes the appearance of a two-handed blunt into that of Drake Maul. 30-day. -->
		<set name="icon" val="BranchSys3.Icon.g_shape_shifting_twohand_blunt" />
		<set name="immediate_effect" val="1" />
		<set name="handler" val="Book" />
		<set name="default_action" val="skill_reduce" />
		<set name="etcitem_type" val="none" />
		<set name="is_stackable" val="true" />
		<set name="material" val="paper" />
		<set name="item_skill" val="18404-1" />
		<!-- Drake Maul Appearance Stone -->
	</item>
	<item id="46109" type="EtcItem" nameRu="Камень Обработки Посоха Фреи" nameEn="Freya's Staff Appearance Stone">
		<!-- Позволяет на 30 д. придать двуручному дробящему оружию вид Посоха Фреи. -->
		<!-- Changes the appearance of a two-handed magic blunt into that of Freya's Staff. 30-day. -->
		<set name="icon" val="icon.shape_shifting_magic_twohand_blunt_i00" />
		<set name="immediate_effect" val="1" />
		<set name="handler" val="Book" />
		<set name="default_action" val="skill_reduce" />
		<set name="etcitem_type" val="none" />
		<set name="is_stackable" val="true" />
		<set name="material" val="paper" />
		<set name="item_skill" val="18405-1" />
		<!-- Freya's Staff Appearance Stone -->
	</item>
	<item id="46110" type="EtcItem" nameRu="Камень Обработки Когтя Спасии" nameEn="Spezion's Claw Appearance Stone">
		<!-- Позволяет на 30 д. придать двуручным кастетам вид Когтя Спасии. -->
		<!-- Changes the appearance of a two-handed fist weapon into that of Spezion's Claw. 30-day. -->
		<set name="icon" val="BranchSys3.Icon.g_shape_shifting_dualfist" />
		<set name="immediate_effect" val="1" />
		<set name="handler" val="Book" />
		<set name="default_action" val="skill_reduce" />
		<set name="etcitem_type" val="none" />
		<set name="is_stackable" val="true" />
		<set name="material" val="paper" />
		<set name="item_skill" val="18406-1" />
		<!-- Spezion's Claw Appearance Stone -->
	</item>
	<item id="46111" type="EtcItem" nameRu="Камень Обработки Буревестника Меллисы" nameEn="Maliss Stormer Appearance Stone">
		<!-- Позволяет на 30 д. придать древковому оружию вид Буревестника Меллисы. -->
		<!-- Changes the appearance of a spear into that of a Maliss Stormer. 30-day. -->
		<set name="icon" val="BranchSys3.Icon.g_shape_shifting_pole" />
		<set name="immediate_effect" val="1" />
		<set name="handler" val="Book" />
		<set name="default_action" val="skill_reduce" />
		<set name="etcitem_type" val="none" />
		<set name="is_stackable" val="true" />
		<set name="material" val="paper" />
		<set name="item_skill" val="18407-1" />
		<!-- Maliss Stormer Appearance Stone -->
	</item>
	<item id="46112" type="EtcItem" nameRu="Камень Обработки Кинжала Стерегоса" nameEn="Steregos' Dagger Appearance Stone">
		<!-- Позволяет на 30 д. придать кинжалу вид Кинжала Стерегоса. -->
		<!-- Changes the appearance of a one handed dagger into that of Steregos' Dagger. 30-day. -->
		<set name="icon" val="BranchSys3.Icon.g_shape_shifting_dagger" />
		<set name="immediate_effect" val="1" />
		<set name="handler" val="Book" />
		<set name="default_action" val="skill_reduce" />
		<set name="etcitem_type" val="none" />
		<set name="is_stackable" val="true" />
		<set name="material" val="paper" />
		<set name="item_skill" val="18408-1" />
		<!-- Steregos' Dagger Appearance Stone -->
	</item>
	<item id="46113" type="EtcItem" nameRu="Камень Обработки Парных Дубин Фрона" nameEn="Ron's Dual Blunt Weapon Appearance Stone">
		<!-- Позволяет на 30 д. придать парному дробящему оружию вид Парных Дубин Фрона. -->
		<!-- Changes the appearance of a dual blunt into that of Ron's Dual Blunt Weapon. 30-day. -->
		<set name="icon" val="BranchSys3.Icon.g_shape_shifting_dualblunt" />
		<set name="immediate_effect" val="1" />
		<set name="handler" val="Book" />
		<set name="default_action" val="skill_reduce" />
		<set name="etcitem_type" val="none" />
		<set name="is_stackable" val="true" />
		<set name="material" val="paper" />
		<set name="item_skill" val="18409-1" />
		<!-- Ron's Dual Blunt Weapon Appearance Stone -->
	</item>
	<item id="46114" type="EtcItem" nameRu="Камень Обработки Булавы Дрейка" nameEn="Drake Maul Appearance Stone">
		<!-- Позволяет придать двуручному дробящему оружию вид Булавы Дрейка. -->
		<!-- Changes the appearance of a two-handed blunt into that of Drake Maul's. -->
		<set name="icon" val="BranchSys3.Icon.g_shape_shifting_twohand_blunt" />
		<set name="immediate_effect" val="1" />
		<set name="handler" val="Book" />
		<set name="default_action" val="skill_reduce" />
		<set name="etcitem_type" val="none" />
		<set name="is_stackable" val="true" />
		<set name="material" val="paper" />
		<set name="item_skill" val="18420-1" />
		<!-- Drake Maul Appearance Stone -->
	</item>
	<item id="46115" type="EtcItem" nameRu="Камень Обработки Посоха Фреи" nameEn="Freya's Staff Appearance Stone">
		<!-- Позволяет придать двуручному дробящему оружию вид Посоха Фреи. -->
		<!-- Changes the appearance of a two-handed magic blunt into that of Freya's Staff. -->
		<set name="icon" val="icon.shape_shifting_magic_twohand_blunt_i00" />
		<set name="immediate_effect" val="1" />
		<set name="handler" val="Book" />
		<set name="default_action" val="skill_reduce" />
		<set name="etcitem_type" val="none" />
		<set name="is_stackable" val="true" />
		<set name="material" val="paper" />
		<set name="item_skill" val="18421-1" />
		<!-- Freya's Staff Appearance Stone -->
	</item>
	<item id="46116" type="EtcItem" nameRu="Камень Обработки Когтя Спасии" nameEn="Spezion's Claw Appearance Stone">
		<!-- Позволяет придать двуручным кастетам вид Когтя Спасии. -->
		<!-- Changes the appearance of a two-handed fist weapon into that of Spezion's Claw. -->
		<set name="icon" val="BranchSys3.Icon.g_shape_shifting_dualfist" />
		<set name="immediate_effect" val="1" />
		<set name="handler" val="Book" />
		<set name="default_action" val="skill_reduce" />
		<set name="etcitem_type" val="none" />
		<set name="is_stackable" val="true" />
		<set name="material" val="paper" />
		<set name="item_skill" val="18422-1" />
		<!-- Spezion's Claw Appearance Stone -->
	</item>
	<item id="46117" type="EtcItem" nameRu="Камень Обработки Буревестника Меллисы" nameEn="Maliss Stormer Appearance Stone">
		<!-- Позволяет придать древковому оружию вид Буревестника Меллисы. -->
		<!-- Changes the appearance of a spear into that of a Maliss Stormer. -->
		<set name="icon" val="BranchSys3.Icon.g_shape_shifting_pole" />
		<set name="immediate_effect" val="1" />
		<set name="handler" val="Book" />
		<set name="default_action" val="skill_reduce" />
		<set name="etcitem_type" val="none" />
		<set name="is_stackable" val="true" />
		<set name="material" val="paper" />
		<set name="item_skill" val="18423-1" />
		<!-- Maliss Stormer Appearance Stone -->
	</item>
	<item id="46118" type="EtcItem" nameRu="Камень Обработки Кинжала Стерегоса" nameEn="Steregos' Dagger Appearance Stone">
		<!-- Позволяет придать кинжалу вид Кинжала Стерегоса. -->
		<!-- Changes the appearance of a one handed dagger into that of Steregos' Dagger. -->
		<set name="icon" val="BranchSys3.Icon.g_shape_shifting_dagger" />
		<set name="immediate_effect" val="1" />
		<set name="handler" val="Book" />
		<set name="default_action" val="skill_reduce" />
		<set name="etcitem_type" val="none" />
		<set name="is_stackable" val="true" />
		<set name="material" val="paper" />
		<set name="item_skill" val="18424-1" />
		<!-- Steregos' Dagger Appearance Stone -->
	</item>
	<item id="46119" type="EtcItem" nameRu="Камень Обработки Парных Дубин Фрона" nameEn="Ron's Dual Blunt Weapon Appearance Stone">
		<!-- Позволяет придать парному дробящему оружию вид Парных Дубин Фрона. -->
		<!-- Changes the appearance of a dual blunt into that of Ron's Dual Blunt Weapon. -->
		<set name="icon" val="BranchSys3.Icon.g_shape_shifting_dualblunt" />
		<set name="immediate_effect" val="1" />
		<set name="handler" val="Book" />
		<set name="default_action" val="skill_reduce" />
		<set name="etcitem_type" val="none" />
		<set name="is_stackable" val="true" />
		<set name="material" val="paper" />
		<set name="item_skill" val="18425-1" />
		<!-- Ron's Dual Blunt Weapon Appearance Stone -->
	</item>
	<item id="46120" type="EtcItem" nameRu="Камень Обработки Детской Шапочки (Ж)" nameEn="Little Girls' Hat Appearance Stone">
		<!-- Позволяет на 30 д. придать головному убору вид Детской Шапочки. Подходит только к головным уборам, занимающим 2 ячейки. Только для персонажей женского пола. -->
		<!-- Changes the appearance of a hair accessory into that of a Little Girl's Hat. 30-day. Can be used only on hair accessories that take up 2 slots. Female only. -->
		<set name="icon" val="BranchSys3.Icon.g_shape_shifting_hair2" />
		<set name="immediate_effect" val="1" />
		<set name="handler" val="Book" />
		<set name="default_action" val="skill_reduce" />
		<set name="etcitem_type" val="none" />
		<set name="is_stackable" val="true" />
		<set name="material" val="steel" />
		<set name="item_skill" val="18410-1" />
		<!-- Little Girls' Hat Appearance Stone -->
	</item>
	<item id="46121" type="EtcItem" nameRu="Камень Обработки Детской Шапочки (М)" nameEn="Little Boy's Hat Appearance Stone">
		<!-- Позволяет на 30 д. придать головному убору вид Детской Шапочки. Подходит только к головным уборам, занимающим 2 ячейки. Только для персонажей мужского пола. -->
		<!-- Changes the appearance of a hair accessory into that of a Little Boy's Hat. 30-day. Can be used only on hair accessories that take up 2 slots. Male only. -->
		<set name="icon" val="BranchSys3.Icon.g_shape_shifting_hair2" />
		<set name="immediate_effect" val="1" />
		<set name="handler" val="Book" />
		<set name="default_action" val="skill_reduce" />
		<set name="etcitem_type" val="none" />
		<set name="is_stackable" val="true" />
		<set name="material" val="steel" />
		<set name="item_skill" val="18411-1" />
		<!-- Little Boy's Hat Appearance Stone -->
	</item>
	<item id="46122" type="EtcItem" nameRu="Камень Обработки Детской Шапочки (Ж)" nameEn="Little Girls' Hat Appearance Stone">
		<!-- Позволяет придать головному убору вид Детской Шапочки. Подходит только к головным уборам, занимающим 2 ячейки. Только для персонажей женского пола. -->
		<!-- Changes the appearance of a hair accessory into that of a Little Girl's Hat. Can be used only on hair accessories that take up 2 slots. Female only. -->
		<set name="icon" val="BranchSys3.Icon.g_shape_shifting_hair2" />
		<set name="immediate_effect" val="1" />
		<set name="handler" val="Book" />
		<set name="default_action" val="skill_reduce" />
		<set name="etcitem_type" val="none" />
		<set name="is_stackable" val="true" />
		<set name="material" val="steel" />
		<set name="item_skill" val="18412-1" />
		<!-- Little Girls' Hat Appearance Stone -->
	</item>
	<item id="46123" type="EtcItem" nameRu="Камень Обработки Детской Шапочки (М)" nameEn="Little Boy's Hat Appearance Stone">
		<!-- Позволяет придать головному убору вид Детской Шапочки. Подходит только к головным уборам, занимающим 2 ячейки. Только для персонажей мужского пола. -->
		<!-- Changes the appearance of a hair accessory into that of a Little Boy's Hat. Can be used only on hair accessories that take up 2 slots. Male only. -->
		<set name="icon" val="BranchSys3.Icon.g_shape_shifting_hair2" />
		<set name="immediate_effect" val="1" />
		<set name="handler" val="Book" />
		<set name="default_action" val="skill_reduce" />
		<set name="etcitem_type" val="none" />
		<set name="is_stackable" val="true" />
		<set name="material" val="steel" />
		<set name="item_skill" val="18413-1" />
		<!-- Little Boy's Hat Appearance Stone -->
	</item>
	<item id="46124" type="EtcItem" nameRu="Камень Обработки Форменного Головного Убора" nameEn="Uniform Hat Appearance Stone">
		<!-- Позволяет на 30 д. придать головному убору вид Форменного Головного Убора. Подходит только к головным уборам, занимающим 2 ячейки. -->
		<!-- Changes the appearance of a hair accessory into that of a Uniform Hat. 30-day. Can be used only on hair accessories that take up 2 slots. -->
		<set name="icon" val="BranchSys3.Icon.g_shape_shifting_hair2" />
		<set name="immediate_effect" val="1" />
		<set name="handler" val="Book" />
		<set name="default_action" val="skill_reduce" />
		<set name="etcitem_type" val="none" />
		<set name="is_stackable" val="true" />
		<set name="material" val="steel" />
		<set name="item_skill" val="18414-1" />
		<!-- Uniform Hat Appearance Stone -->
	</item>
	<item id="46125" type="EtcItem" nameRu="Камень Обработки Золотого Афроамериканского Парика" nameEn="Afro - Gold Appearance Stone">
		<!-- Позволяет на 30 д. придать головному убору вид Золотого Афроамериканского Парика. Подходит только к головным уборам, занимающим 2 ячейки. -->
		<!-- Changes the appearance of a hair accessory into that of a Gold Afro. 30-day. Can be used only on hair accessories that take up 2 slots. -->
		<set name="icon" val="BranchSys3.Icon.g_shape_shifting_hair2" />
		<set name="immediate_effect" val="1" />
		<set name="handler" val="Book" />
		<set name="default_action" val="skill_reduce" />
		<set name="etcitem_type" val="none" />
		<set name="is_stackable" val="true" />
		<set name="material" val="steel" />
		<set name="item_skill" val="18415-1" />
		<!-- Afro - Gold Appearance Stone -->
	</item>
	<item id="46126" type="EtcItem" nameRu="Камень Обработки Розового Афроамериканского Парика" nameEn="Afro - Pink Appearance Stone">
		<!-- Позволяет на 30 д. придать головному убору вид Розового Афроамериканского Парика. Подходит только к головным уборам, занимающим 2 ячейки. -->
		<!-- Changes the appearance of a hair accessory into that of a Pink Afro. 30-day. Can be used only on hair accessories that take up 2 slots. -->
		<set name="icon" val="BranchSys3.Icon.g_shape_shifting_hair2" />
		<set name="immediate_effect" val="1" />
		<set name="handler" val="Book" />
		<set name="default_action" val="skill_reduce" />
		<set name="etcitem_type" val="none" />
		<set name="is_stackable" val="true" />
		<set name="material" val="steel" />
		<set name="item_skill" val="18416-1" />
		<!-- Afro - Pink Appearance Stone -->
	</item>
	<item id="46127" type="EtcItem" nameRu="Камень Обработки Форменного Головного Убора" nameEn="Uniform Hat Appearance Stone">
		<!-- Позволяет придать головному убору вид Форменного Головного Убора. Подходит только к головным уборам, занимающим 2 ячейки. -->
		<!-- Changes the appearance of a hair accessory into that of a Uniform Hat. Can be used only on hair accessories that take up 2 slots. -->
		<set name="icon" val="BranchSys3.Icon.g_shape_shifting_hair2" />
		<set name="immediate_effect" val="1" />
		<set name="handler" val="Book" />
		<set name="default_action" val="skill_reduce" />
		<set name="etcitem_type" val="none" />
		<set name="is_stackable" val="true" />
		<set name="material" val="steel" />
		<set name="item_skill" val="18417-1" />
		<!-- Uniform Hat Appearance Stone -->
	</item>
	<item id="46128" type="EtcItem" nameRu="Камень Обработки Золотого Афроамериканского Парика" nameEn="Afro - Gold Appearance Stone">
		<!-- Позволяет придать головному убору вид Золотого Афроамериканского Парика. Подходит только к головным уборам, занимающим 2 ячейки. -->
		<!-- Changes the appearance of a hair accessory into that of a Gold Afro. Can be used only on hair accessories that take up 2 slots. -->
		<set name="icon" val="BranchSys3.Icon.g_shape_shifting_hair2" />
		<set name="immediate_effect" val="1" />
		<set name="handler" val="Book" />
		<set name="default_action" val="skill_reduce" />
		<set name="etcitem_type" val="none" />
		<set name="is_stackable" val="true" />
		<set name="material" val="steel" />
		<set name="item_skill" val="18418-1" />
		<!-- Afro - Gold Appearance Stone -->
	</item>
	<item id="46129" type="EtcItem" nameRu="Камень Обработки Розового Афроамериканского Парика" nameEn="Afro - Pink Appearance Stone">
		<!-- Позволяет придать головному убору вид Розового Афроамериканского Парика. Подходит только к головным уборам, занимающим 2 ячейки. -->
		<!-- Changes the appearance of a hair accessory into that of a Pink Afro. Can be used only on hair accessories that take up 2 slots. -->
		<set name="icon" val="BranchSys3.Icon.g_shape_shifting_hair2" />
		<set name="immediate_effect" val="1" />
		<set name="handler" val="Book" />
		<set name="default_action" val="skill_reduce" />
		<set name="etcitem_type" val="none" />
		<set name="is_stackable" val="true" />
		<set name="material" val="steel" />
		<set name="item_skill" val="18419-1" />
		<!-- Afro - Pink Appearance Stone -->
	</item>
	<item id="46130" type="EtcItem" nameRu="Осколок Разума Духа" nameEn="Spirit Evil Thought Piece">
		<!-- Осколок Разума Духа, выроненный Эль Флото. Позволяет открыть дверь, ведущую к Харпе в Храме Духов. -->
		<!-- A piece of El Floato's evil thoughts. Use it to open the door to get to Harpe in the Garden of Spirits. -->
		<set name="icon" val="icon.etc_ertheia_prophecy_device_piece" />
		<set name="is_sellable" val="false" />
		<set name="etcitem_type" val="scroll" />
		<set name="is_stackable" val="true" />
		<set name="material" val="leather" />
	</item>
	<item id="46131" type="Weapon" nameRu="Оружие Кельбима" nameEn="Kelbim Exclusive Weapon">
		<!-- Оружие Кельбима -->
		<!-- Exclusive weapon of Kelbim. -->
		<set name="icon" val="icon.weapon_monster_i00" />
		<set name="weapon_type" val="bow" />
		<set name="default_action" val="equip" />
		<set name="crystal_type" val="d" />
		<set name="soulshots" val="2" />
		<set name="spiritshots" val="2" />
		<set name="bodypart" val="lrhand" />
		<set name="weight" val="300" />
		<set name="material" val="steel" />
		<set name="attack_range" val="500" />
		<set name="random_damage" val="5" />
		<for>
			<set order="0x08" stat="pAtk" val="5" />
			<set order="0x08" stat="mAtk" val="5" />
			<set order="0x08" stat="pAtkSpd" val="433" />
			<set order="0x08" stat="rCrit" val="12" />
			<add order="0x10" stat="accCombat" val="-3.75" />
		</for>
	</item>
	<item id="46132" type="EtcItem" nameRu="Печать Блэкбердов" nameEn="Blackbird Seal">
		<!-- Печать, символизирующая принадлежность к клану Блэкбердов. Обладатель печати либо является членом клана, либо заслужил его доверие. -->
		<!-- Seal that proves that one is a member of the Blackbird Clan. The seal proves that one is a member of the clan or is someone trusted by the clan. -->
		<set name="icon" val="icon.etc_piece_holy_light" />
		<set name="is_tradable" val="false" />
		<set name="is_dropable" val="false" />
		<set name="is_destroyable" val="false" />
		<set name="is_sellable" val="false" />
		<set name="is_questitem" val="true" />
		<set name="is_depositable" val="false" />
		<set name="material" val="paper" />
	</item>
	<item id="46133" type="EtcItem" nameRu="Нейтрализатор Астатина Тьмы" nameEn="Dark Atelia Neutralizer">
		<!-- Нейтрализатор, защищающий от ядовитых веществ, выделяющихся при создании Астатина Тьмы. Все Эмбрио в Крепости Астатина имеют такой при себе. -->
		<!-- A neutralizer that prevents addiction of the by-product that is produced when creating Dark Atelia. All the Embryo in the Atelia Fortress carry this neutralizer. -->
		<set name="icon" val="icon.etc_potion_yellow_i00" />
		<set name="is_tradable" val="false" />
		<set name="is_dropable" val="false" />
		<set name="is_destroyable" val="false" />
		<set name="is_sellable" val="false" />
		<set name="is_questitem" val="true" />
		<set name="is_stackable" val="true" />
		<set name="is_depositable" val="false" />
		<set name="material" val="paper" />
	</item>
	<item id="46134" type="EtcItem" nameRu="Отчет Блэкбердов - Гленхинчи" nameEn="Blackbird Report - Glenkinchie">
		<!-- Отчет Гленхинчи из клана Блэкбердов, составленный для Элрики. Содержит информацию об Эмбрио.  -->
		<!-- Glenkinchie's report to Elikia. It says stuff about the Embryo. -->
		<set name="icon" val="icon.etc_scroll_gray_i00" />
		<set name="is_tradable" val="false" />
		<set name="is_dropable" val="false" />
		<set name="is_destroyable" val="false" />
		<set name="is_sellable" val="false" />
		<set name="is_questitem" val="true" />
		<set name="is_depositable" val="false" />
		<set name="material" val="paper" />
	</item>
	<item id="46135" type="EtcItem" nameRu="Отчет Блэкбердов - Хурак" nameEn="Blackbird Report - Hurak">
		<!-- Отчет Хурака из клана Блэкбердов, составленный для Элрики. Содержит информацию об Эмбрио.  -->
		<!-- Hurak's report to Elikia. It says stuff about the Embryo. -->
		<set name="icon" val="icon.etc_scroll_gray_i00" />
		<set name="is_tradable" val="false" />
		<set name="is_dropable" val="false" />
		<set name="is_destroyable" val="false" />
		<set name="is_sellable" val="false" />
		<set name="is_questitem" val="true" />
		<set name="is_depositable" val="false" />
		<set name="material" val="paper" />
	</item>
	<item id="46136" type="EtcItem" nameRu="Отчет Блэкбердов - Рафиан" nameEn="Blackbird Report - Laffian">
		<!-- Отчет Рафиан из клана Блэкбердов, составленный для Элрики. Содержит информацию об Эмбрио.  -->
		<!-- Laffian's report to Elikia. It says stuff about the Embryo. -->
		<set name="icon" val="icon.etc_scroll_gray_i00" />
		<set name="is_tradable" val="false" />
		<set name="is_dropable" val="false" />
		<set name="is_destroyable" val="false" />
		<set name="is_sellable" val="false" />
		<set name="is_questitem" val="true" />
		<set name="is_depositable" val="false" />
		<set name="material" val="paper" />
	</item>
	<item id="46137" type="EtcItem" nameRu="Отчет Блэкбердов - Шери" nameEn="Blackbird Report - Sherry">
		<!-- Отчет Шери из клана Блэкбердов, составленный для Элрики. Содержит информацию об Эмбрио.  -->
		<!-- Sherry's report to Elikia. It says stuff about the Embryo. -->
		<set name="icon" val="icon.etc_scroll_gray_i00" />
		<set name="is_tradable" val="false" />
		<set name="is_dropable" val="false" />
		<set name="is_destroyable" val="false" />
		<set name="is_sellable" val="false" />
		<set name="is_questitem" val="true" />
		<set name="is_depositable" val="false" />
		<set name="material" val="paper" />
	</item>
	<item id="46138" type="EtcItem" nameRu="Сертификат Почетного Члена Авангарда Адена I" nameEn="Low-grade Honorary Member Certificate">
		<!-- Сертификат, подтверждающий почетное членство в Авангарде Адена. В данный момент не все члены Авангарда признают его. -->
		<!-- A certificate that proves that you are an honorary member of the Aden Vanguard. You haven't been recognized by every member yet. -->
		<set name="icon" val="icon.etc_london_olympic_bronze" />
		<set name="is_depositable" val="false" />
		<set name="is_tradable" val="false" />
		<set name="is_dropable" val="false" />
		<set name="is_destroyable" val="false" />
		<set name="is_sellable" val="false" />
		<set name="is_questitem" val="true" />
		<set name="material" val="paper" />
	</item>
	<item id="46139" type="EtcItem" nameRu="Сертификат Почетного Члена Авангарда Адена I" nameEn="Low-grade Honorary Member Certificate">
		<!-- Сертификат, подтверждающий почетное членство в Авангарде Адена. В данный момент не все члены Авангарда признают его. -->
		<!-- A certificate that proves that you are an honorary member of the Aden Vanguard. You haven't been recognized by every member yet. -->
		<set name="icon" val="icon.etc_london_olympic_bronze" />
		<set name="is_depositable" val="false" />
		<set name="is_tradable" val="false" />
		<set name="is_dropable" val="false" />
		<set name="is_destroyable" val="false" />
		<set name="is_sellable" val="false" />
		<set name="is_questitem" val="true" />
		<set name="material" val="paper" />
	</item>
	<item id="46140" type="EtcItem" nameRu="Сертификат Почетного Члена Авангарда Адена I" nameEn="Low-grade Honorary Member Certificate">
		<!-- Сертификат, подтверждающий почетное членство в Авангарде Адена. В данный момент не все члены Авангарда признают его. -->
		<!-- A certificate that proves that you are an honorary member of the Aden Vanguard. You haven't been recognized by every member yet. -->
		<set name="icon" val="icon.etc_london_olympic_bronze" />
		<set name="is_depositable" val="false" />
		<set name="is_tradable" val="false" />
		<set name="is_dropable" val="false" />
		<set name="is_destroyable" val="false" />
		<set name="is_sellable" val="false" />
		<set name="is_questitem" val="true" />
		<set name="material" val="paper" />
	</item>
	<item id="46141" type="EtcItem" nameRu="Сертификат Почетного Члена Авангарда Адена II" nameEn="Mid-grade Honorary Member Certificate">
		<!-- Сертификат, ранее подтверждавший почетное членство в Авангарде Адена. Больше не признается Имперскими Гвардейцами и не используются. -->
		<!-- A certificate that informs you that you are an honorary member of the Aden Vanguard. The Kingdom's Royal Guard recognition was not received, and can no longer be used. -->
		<set name="icon" val="icon.etc_london_olympic_silver" />
		<set name="is_depositable" val="false" />
		<set name="is_tradable" val="false" />
		<set name="is_dropable" val="false" />
		<set name="is_destroyable" val="false" />
		<set name="is_sellable" val="false" />
		<set name="is_questitem" val="true" />
		<set name="material" val="paper" />
	</item>
	<item id="46142" type="EtcItem" nameRu="Кусок Ткани для Починки Знамени" nameEn="Stronghold Flag Repair Supplies">
		<!-- Кусок ткани, нужный для починки знамени базы. Отнесите его в ставку Авангарда Адена. -->
		<!-- A piece of cloth to fix the flag that represents the stronghold. Take it to the Aden Vanguard. -->
		<set name="icon" val="icon.etc_piece_of_cloth_white_i00" />
		<set name="is_tradable" val="false" />
		<set name="is_dropable" val="false" />
		<set name="is_destroyable" val="false" />
		<set name="is_sellable" val="false" />
		<set name="is_questitem" val="true" />
		<set name="is_stackable" val="true" />
		<set name="is_depositable" val="false" />
		<set name="material" val="paper" />
	</item>
	<item id="46143" type="EtcItem" nameRu="Устройство для Ремонта Базы" nameEn="Stronghold Repair Tools">
		<!-- Устройство, при помощи которого можно отремонтировать разрушенную базу. Отнесите его в ставку Авангарда Адена. -->
		<!-- Tools to repair the stronghold. Take it to the Aden Stronghold. -->
		<set name="icon" val="icon.etc_squares_gray_i00" />
		<set name="is_tradable" val="false" />
		<set name="is_dropable" val="false" />
		<set name="is_destroyable" val="false" />
		<set name="is_sellable" val="false" />
		<set name="is_questitem" val="true" />
		<set name="is_depositable" val="false" />
		<set name="material" val="paper" />
	</item>
	<item id="46144" type="EtcItem" nameRu="Деталь Доспеха Кельбима" nameEn="Kelbim's Armor Piece">
		<!-- Отвалившаяся деталь доспеха Кельбима. Кейсия полагает, что она должна помочь понять, как Эмбрио используют Астатин. Доставьте деталь Кейсии в Орен. -->
		<!-- A piece of the armor that Kelbim was wearing. Kaysia needs it in order to find out what the Embryo are using the Atelia for. Take it to Kaysia in the Town of Oren. -->
		<set name="icon" val="icon.etc_plate_black_i00" />
		<set name="is_tradable" val="false" />
		<set name="is_dropable" val="false" />
		<set name="is_destroyable" val="false" />
		<set name="is_sellable" val="false" />
		<set name="is_questitem" val="true" />
		<set name="is_depositable" val="false" />
		<set name="material" val="paper" />
	</item>
	<item id="46145" type="EtcItem" nameRu="Порошок Черного Астатина" nameEn="Black Atelia Powder">
		<!-- Порошок, осыпавшийся с гигантского Астатина черного цвета. Наверняка порошок прольет свет на различия Астатина в крепости от Астатина из Мира Духов. Отнесите его Кейсии в Орен. -->
		<!-- Powder from the Giant Atelia that turned black. It will be useful in finding out how it's different from the Atelia of the Wind Spirit Realm. Take it to Kaysia in the Town of Oren. -->
		<set name="icon" val="icon.etc_powder_black_i00" />
		<set name="is_tradable" val="false" />
		<set name="is_dropable" val="false" />
		<set name="is_destroyable" val="false" />
		<set name="is_sellable" val="false" />
		<set name="is_questitem" val="true" />
		<set name="is_depositable" val="false" />
		<set name="material" val="paper" />
	</item>
	<item id="46146" type="EtcItem" nameRu="Устройство Перемещения на 1-ю Базу Крепости Астатина" nameEn="Atelia Fortress Stronghold I Teleport Device">
		<!-- Устройство для перемещения к 1-й Базе. Поставляется из Адена для удобства перемещения. Из-за нестабильного состояния Крепости Астатина пользоваться им можно лишь в течение 24 ч. -->
		<!-- A teleport device that takes you to Stronghold I. It was brought from Aden in order to facilitate movement. Because of the instability in the Atelia Fortress, it can only be used for 24 hours. -->
		<set name="icon" val="icon.etc_mechanic_box_i00" />
		<set name="is_tradable" val="false" />
		<set name="is_dropable" val="false" />
		<set name="is_destroyable" val="false" />
		<set name="is_sellable" val="false" />
		<set name="weight" val="150" />
		<set name="time" val="1440" />
		<set name="material" val="steel" />
	</item>
	<item id="46147" type="EtcItem" nameRu="Устройство Перемещения на 2-ю Базу Крепости Астатина" nameEn="Atelia Fortress Stronghold II Teleport Device">
		<!-- Устройство для перемещения ко 2-й Базе. Поставляется из Адена для удобства перемещения. Из-за нестабильного состояния Крепости Астатина пользоваться им можно лишь в течение 24 ч. -->
		<!-- A teleport device that takes you to Stronghold II. It was brought from Aden in order to facilitate movement. Because of the instability in the Atelia Fortress, it can only be used for 24 hours. -->
		<set name="icon" val="icon.etc_mechanic_box_i00" />
		<set name="is_tradable" val="false" />
		<set name="is_dropable" val="false" />
		<set name="is_destroyable" val="false" />
		<set name="is_sellable" val="false" />
		<set name="weight" val="150" />
		<set name="time" val="1440" />
		<set name="material" val="steel" />
	</item>
	<item id="46148" type="EtcItem" nameRu="Устройство Перемещения на 3-ю Базу Крепости Астатина" nameEn="Atelia Fortress Stronghold III Teleport Device">
		<!-- Устройство для перемещения к 3-й Базе. Поставляется из Адена для удобства перемещения. Из-за нестабильного состояния Крепости Астатина пользоваться им можно лишь в течение 24 ч. -->
		<!-- A teleport device that takes you to Stronghold III. It was brought from Aden in order to facilitate movement. Because of the instability in the Atelia Fortress, it can only be used for 24 hours. -->
		<set name="icon" val="icon.etc_mechanic_box_i00" />
		<set name="is_tradable" val="false" />
		<set name="is_dropable" val="false" />
		<set name="is_destroyable" val="false" />
		<set name="is_sellable" val="false" />
		<set name="weight" val="150" />
		<set name="time" val="1440" />
		<set name="material" val="steel" />
	</item>
	<item id="46149" type="EtcItem" nameRu="Устройство Перемещения на 4-ю Базу Крепости Астатина" nameEn="Atelia Fortress Stronghold IV Teleport Device">
		<!-- Устройство для перемещения к 4-й Базе. Поставляется из Адена для удобства перемещения. Из-за нестабильного состояния Крепости Астатина пользоваться им можно лишь в течение 24 ч. -->
		<!-- A teleport device that takes you to Stronghold IV. It was brought from Aden in order to facilitate movement. Because of the instability in the Atelia Fortress, it can only be used for 24 hours. -->
		<set name="icon" val="icon.etc_mechanic_box_i00" />
		<set name="is_tradable" val="false" />
		<set name="is_dropable" val="false" />
		<set name="is_destroyable" val="false" />
		<set name="is_sellable" val="false" />
		<set name="weight" val="150" />
		<set name="time" val="1440" />
		<set name="material" val="steel" />
	</item>
	<item id="46150" type="EtcItem" nameRu="Кодекс Перерождения Глава 1" nameEn="Superior Giant's Codex - Chapter 1">
		<!-- Кодекс Перерождения. Редкий предмет для улучшения умений в диапазоне от +11 до +20 после перерождения. -->
		<!-- Superior Giant's Codex. Rare item needed for enchanting skills between +11~+20 after Awakening. -->
		<set name="icon" val="icon.codex_of_incuse" />
		<set name="weight" val="10" />
		<set name="is_sellable" val="false" />
		<set name="is_stackable" val="true" />
		<set name="material" val="paper" />
	</item>
	<item id="46151" type="EtcItem" nameRu="Кодекс Перерождения - Мастерство Глава 1" nameEn="Superior Giant's Codex - Mastery Chapter 1">
		<!-- Кодекс Перерождения. Редкий предмет для благ. улучшения умений в диапазоне от +11 до +20 после перерождения. -->
		<!-- Superior Giant's Codex. Rare item needed for +21~+30 blessed skill enchantment after Awakening. -->
		<set name="icon" val="icon.codex_of_incuse_dexterity" />
		<set name="weight" val="10" />
		<set name="is_sellable" val="false" />
		<set name="is_stackable" val="true" />
		<set name="material" val="paper" />
	</item>
	<item id="46152" type="EtcItem" nameRu="Кодекс Перерождения - Дисциплина Глава 1" nameEn="Superior Giant's Codex - Discipline Chapter 1">
		<!-- Кодекс Перерождения. Редкий предмет для смены пути улучшения умений в диапазоне от +11 до +20 после перерождения. -->
		<!-- Superior Giant's Codex. Rare item needed for changing enchantment paths for skills between +11~+20 after Awakening. -->
		<set name="icon" val="icon.codex_of_incuse_training" />
		<set name="weight" val="10" />
		<set name="is_sellable" val="false" />
		<set name="is_stackable" val="true" />
		<set name="material" val="paper" />
	</item>
	<item id="46153" type="EtcItem" nameRu="Кодекс Постоянства Глава 1" nameEn="Immortal Scroll Chapter 1">
		<!-- Позволяет с шансом 100% улучшить умение в диапазоне от +11 до +20 без использования дополнительных расходных материалов. -->
		<!-- Enchants a skill between +11~+20 to the next grade with a success rate of 100% without consuming extra materials. -->
		<set name="icon" val="icon.esagira_telepo_01" />
		<set name="weight" val="10" />
		<set name="is_tradable" val="false" />
		<set name="is_dropable" val="false" />
		<set name="is_destroyable" val="false" />
		<set name="is_sellable" val="false" />
		<set name="is_stackable" val="true" />
		<set name="material" val="paper" />
	</item>
	<item id="46154" type="EtcItem" nameRu="Кодекс Перерождения Глава 2" nameEn="Superior Giant's Codex - Chapter 2">
		<!-- Кодекс Перерождения. Редкий предмет для улучшения умений в диапазоне от +21 до +30 после перерождения. -->
		<!-- Superior Giant's Codex. Rare item needed for enchanting skills between +21~+30 after Awakening. -->
		<set name="icon" val="icon.codex_of_incuse" />
		<set name="weight" val="10" />
		<set name="is_sellable" val="false" />
		<set name="is_stackable" val="true" />
		<set name="material" val="paper" />
	</item>
	<item id="46155" type="EtcItem" nameRu="Кодекс Перерождения - Мастерство Глава 2" nameEn="Superior Giant's Codex - Mastery Chapter 2">
		<!-- Кодекс Перерождения. Редкий предмет для благ. улучшения умений в диапазоне от +21 до +30 после перерождения. -->
		<!-- Superior Giant's Codex. Rare item needed for +21~+30 blessed skill enchantment after Awakening. -->
		<set name="icon" val="icon.codex_of_incuse_dexterity" />
		<set name="weight" val="10" />
		<set name="is_sellable" val="false" />
		<set name="is_stackable" val="true" />
		<set name="material" val="paper" />
	</item>
	<item id="46156" type="EtcItem" nameRu="Кодекс Перерождения - Дисциплина Глава 2" nameEn="Superior Giant's Codex - Discipline Chapter 2">
		<!-- Кодекс Перерождения. Редкий предмет для смены пути улучшения умений в диапазоне от +21 до +30 после перерождения. -->
		<!-- Superior Giant's Codex. Rare item needed for changing enchantment paths for skills between +21~+30 after Awakening. -->
		<set name="icon" val="icon.codex_of_incuse_training" />
		<set name="weight" val="10" />
		<set name="is_sellable" val="false" />
		<set name="is_stackable" val="true" />
		<set name="material" val="paper" />
	</item>
	<item id="46157" type="EtcItem" nameRu="Кодекс Постоянства Глава 2" nameEn="Immortal Scroll Chapter 2">
		<!-- Позволяет с шансом 100% улучшить умение +21 - +30 без использования дополнительных расходных материалов. -->
		<!-- Enchants a skill between +21~+30 to the next grade with a success rate of 100% without consuming extra materials. -->
		<set name="icon" val="icon.esagira_telepo_01" />
		<set name="weight" val="10" />
		<set name="is_tradable" val="false" />
		<set name="is_dropable" val="false" />
		<set name="is_destroyable" val="false" />
		<set name="is_sellable" val="false" />
		<set name="is_stackable" val="true" />
		<set name="material" val="paper" />
	</item>
	<item id="46158" type="EtcItem" nameRu="Свиток Телепорта: Лагерь Блэкберд" nameEn="Scroll of Escape: Blackbird Campsite">
		<!-- Свиток телепорта в Лагерь Блэкберд. -->
		<!-- Scroll for teleporting to Blackbird Campsite. -->
		<set name="icon" val="icon.etc_scroll_of_return_i00" />
		<set name="default_action" val="skill_reduce" />
		<set name="material" val="paper" />
		<set name="weight" val="30" />
		<set name="is_stackable" val="true" />
		<set name="is_oly_restricted" val="true" />
		<set name="handler" val="ItemSkills" />
		<!-- <set name="commissionItemType" val="SCROLL_OTHER" \> -->
		<set name="item_skill" val="18426-1" />
		<!-- Scroll of Escape: Blackbird Campsite -->
		<cond addName="1" msgId="113">
			<player flyMounted="false" />
		</cond>
	</item>
	<item id="46159" type="EtcItem" nameRu="Сертификат Почетного Члена Авангарда Адена II" nameEn="Mid-grade Honorary Member Certificate">
		<!-- Сертификат, ранее подтверждавший почетное членство в Авангарде Адена. Больше не признается Имперскими Гвардейцами и не используются. -->
		<!-- A certificate that informs you that you are an honorary member of the Aden Vanguard. The Kingdom's Royal Guard recognition was not received, and can no longer be used. -->
		<set name="icon" val="icon.etc_london_olympic_silver" />
		<set name="is_depositable" val="false" />
		<set name="is_tradable" val="false" />
		<set name="is_dropable" val="false" />
		<set name="is_destroyable" val="false" />
		<set name="is_sellable" val="false" />
		<set name="is_questitem" val="true" />
		<set name="material" val="paper" />
	</item>
	<item id="46160" type="EtcItem" nameRu="Сертификат Почетного Члена Авангарда Адена II" nameEn="Mid-grade Honorary Member Certificate">
		<!-- Сертификат, ранее подтверждавший почетное членство в Авангарде Адена. Больше не признается Имперскими Гвардейцами и не используются. -->
		<!-- A certificate that informs you that you are an honorary member of the Aden Vanguard. The Kingdom's Royal Guard recognition was not received, and can no longer be used. -->
		<set name="icon" val="icon.etc_london_olympic_silver" />
		<set name="is_depositable" val="false" />
		<set name="is_tradable" val="false" />
		<set name="is_dropable" val="false" />
		<set name="is_destroyable" val="false" />
		<set name="is_sellable" val="false" />
		<set name="is_questitem" val="true" />
		<set name="material" val="paper" />
	</item>
	<item id="46161" type="EtcItem" nameRu="Сертификат Почетного Члена Авангарда Адена II" nameEn="Mid-grade Honorary Member Certificate">
		<!-- Сертификат, ранее подтверждавший почетное членство в Авангарде Адена. Больше не признается Имперскими Гвардейцами и не используются. -->
		<!-- A certificate that informs you that you are an honorary member of the Aden Vanguard. The Kingdom's Royal Guard recognition was not received, and can no longer be used. -->
		<set name="icon" val="icon.etc_london_olympic_silver" />
		<set name="is_depositable" val="false" />
		<set name="is_tradable" val="false" />
		<set name="is_dropable" val="false" />
		<set name="is_destroyable" val="false" />
		<set name="is_sellable" val="false" />
		<set name="is_questitem" val="true" />
		<set name="material" val="paper" />
	</item>
	<item id="46162" type="EtcItem" nameRu="Сертификат Почетного Члена Авангарда Адена II" nameEn="Mid-grade Honorary Member Certificate">
		<!-- Сертификат, ранее подтверждавший почетное членство в Авангарде Адена. Больше не признается Имперскими Гвардейцами и не используются. -->
		<!-- A certificate that informs you that you are an honorary member of the Aden Vanguard. The Kingdom's Royal Guard recognition was not received, and can no longer be used. -->
		<set name="icon" val="icon.etc_london_olympic_silver" />
		<set name="is_depositable" val="false" />
		<set name="is_tradable" val="false" />
		<set name="is_dropable" val="false" />
		<set name="is_destroyable" val="false" />
		<set name="is_sellable" val="false" />
		<set name="is_questitem" val="true" />
		<set name="material" val="paper" />
	</item>
	<item id="46163" type="EtcItem" nameRu="Сертификат Почетного Члена Авангарда Адена III" nameEn="High-grade Honorary Member Certificate">
		<!-- Сертификат, ранее подтверждавший почетное членство в Авангарде Адена. Больше не признается Имперскими Гвардейцами и не используются. -->
		<!-- A certificate that informs you that you are an honorary member of the Aden Vanguard. The Kingdom's Royal Guard recognition was not received, and can no longer be used. -->
		<set name="icon" val="icon.etc_london_olympic_gold" />
		<set name="is_depositable" val="false" />
		<set name="is_tradable" val="false" />
		<set name="is_dropable" val="false" />
		<set name="is_destroyable" val="false" />
		<set name="is_sellable" val="false" />
		<set name="is_questitem" val="true" />
		<set name="material" val="paper" />
	</item>
	<item id="46164" type="EtcItem" nameRu="Сундук с Наградой Авангарда Адена" nameEn="Aden Vanguard Reward Box">
		<!-- Сундук с наградой за заслуги перед Авангардом Адена. Открытие двойным щелчком мыши. -->
		<!-- A reward for finishing the missions as an honorary member of the Aden Vanguard. Double-click to use. -->
		<set name="icon" val="icon.etc_box_of_adventure_3_i00" />
		<set name="is_tradable" val="false" />
		<set name="is_dropable" val="false" />
		<set name="is_sellable" val="false" />
		<set name="is_stackable" val="true" />
		<set name="material" val="paper" />
	</item>
	<item id="46165" type="EtcItem" nameRu="Сундук с Наградой Эфиры" nameEn="Ferin's Reward Box">
		<!-- Сундук с наградой за помощь Эфире Де Ган и ее единомышленникам. Открытие двойным щелчком. -->
		<!-- Reward for helping Ferin and her people. Double-click to open. -->
		<set name="icon" val="icon.etc_box_of_adventure_3_i00" />
		<set name="is_tradable" val="false" />
		<set name="is_dropable" val="false" />
		<set name="is_sellable" val="false" />
		<set name="is_stackable" val="true" />
		<set name="material" val="paper" />
	</item>
	<item id="46166" type="EtcItem" nameRu="Письмо Бартона" nameEn="Barton's Letter">
		<!-- Письмо Бартона с 1-й Базы для Начальника Авангарда Адена Адольфа. Отнесите его Адольфу в Лагерь Блэкберд. -->
		<!-- A letter from the first stronghold's Barton to the Aden Vanguard Captain Adolph. Take it to Adolph in the Blackbird Campsite. -->
		<set name="icon" val="icon.etc_letter_envelope_i00" />
		<set name="is_tradable" val="false" />
		<set name="is_dropable" val="false" />
		<set name="is_sellable" val="false" />
		<set name="is_questitem" val="true" />
		<set name="is_depositable" val="false" />
		<set name="material" val="paper" />
	</item>
	<item id="46167" type="EtcItem" nameRu="Письмо Хаюка" nameEn="Hayuk's Letter">
		<!-- Письмо Хаюка со 2-й Базы для Начальника Авангарда Адена Адольфа. Отнесите его Адольфу в Лагерь Блэкберд. -->
		<!-- A letter from the second stronghold's Hayuk to the Aden Vanguard Captain Adolph. Take it to Adolph in the Blackbird Campsite. -->
		<set name="icon" val="icon.etc_letter_envelope_i00" />
		<set name="is_tradable" val="false" />
		<set name="is_dropable" val="false" />
		<set name="is_sellable" val="false" />
		<set name="is_questitem" val="true" />
		<set name="is_depositable" val="false" />
		<set name="material" val="paper" />
	</item>
	<item id="46168" type="EtcItem" nameRu="Письмо Элис" nameEn="Elise's Letter">
		<!-- Письмо Элис с 3-й Базы для Начальника Авангарда Адена Адольфа. Отнесите его Адольфу в Лагерь Блэкберд. -->
		<!-- A letter from the third stronghold's Elise to the Aden Vanguard Captain Adolph. Take it to Adolph in the Blackbird Campsite. -->
		<set name="icon" val="icon.etc_letter_envelope_i00" />
		<set name="is_tradable" val="false" />
		<set name="is_dropable" val="false" />
		<set name="is_sellable" val="false" />
		<set name="is_questitem" val="true" />
		<set name="is_depositable" val="false" />
		<set name="material" val="paper" />
	</item>
	<item id="46169" type="EtcItem" nameRu="Письмо Эллии" nameEn="Eliyah's Letter">
		<!-- Письмо Эллии с 4-й Базы для Начальника Авангарда Адена Адольфа. Отнесите его Адольфу в Лагерь Блэкберд. -->
		<!-- A letter from the fourth stronghold's Elliyah to the Aden Vanguard Captain Adolph. Take it to Adolph in the Blackbird Campsite. -->
		<set name="icon" val="icon.etc_letter_envelope_i00" />
		<set name="is_tradable" val="false" />
		<set name="is_dropable" val="false" />
		<set name="is_sellable" val="false" />
		<set name="is_questitem" val="true" />
		<set name="is_depositable" val="false" />
		<set name="material" val="paper" />
	</item>
	<item id="46170" type="EtcItem" nameRu="Защитный Ящик Крепости Астатина" nameEn="Atelia Fortress Protection Box">
		<!-- Награда ивента "Золотые Игральные Кости Друвы". Будет удалена 19 ноября 2014 г. -->
		<!-- Reward for Drew's Golden Dice event. Will be deleted once the event ends. -->
		<set name="icon" val="BranchSys.br_bright_gold_box_i00" />
		<set name="is_tradable" val="false" />
		<set name="is_dropable" val="false" />
		<set name="is_sellable" val="false" />
		<set name="is_stackable" val="true" />
		<set name="material" val="paper" />
	</item>
	<item id="46171" type="EtcItem" nameRu="Защитный Ящик Храма Духов" nameEn="Garden of the Spirits Protection Box">
		<!-- Награда ивента "Золотые Игральные Кости Друвы". Будет удалена 19 ноября 2014 г. -->
		<!-- Reward for Drew's Golden Dice event. Will be deleted once the event ends. -->
		<set name="icon" val="BranchSys.br_gold_box_i00" />
		<set name="is_tradable" val="false" />
		<set name="is_dropable" val="false" />
		<set name="is_sellable" val="false" />
		<set name="is_stackable" val="true" />
		<set name="material" val="paper" />
	</item>
	<item id="46172" type="EtcItem" nameRu="Защитный Ящик Друвы" nameEn="Drew Protection Box">
		<!-- Награда ивента "Золотые Игральные Кости Друвы". Будет удалена 19 ноября 2014 г. -->
		<!-- Reward for Drew's Golden Dice event. Will be deleted once the event ends. -->
		<set name="icon" val="BranchSys.br_silver_box_i00" />
		<set name="is_tradable" val="false" />
		<set name="is_dropable" val="false" />
		<set name="is_sellable" val="false" />
		<set name="is_stackable" val="true" />
		<set name="material" val="paper" />
	</item>
	<item id="46173" type="EtcItem" nameRu="Камень Обработки Мужского Купального Костюма No.1" nameEn="Male Swimsuit No.1 Appearance Stone">
		<!-- Позволяет изменить вид нагрудника на Мужской Купальный костюм No.1. Можно использовать на полном доспехе. Полностью изменяет облик доспехов. Камень восстановления возвращает предметам прежний вид. -->
		<!-- Changes the appearance of upper armor into that of Male Swimwear No. 1. Works on one-pieces too. It modifies everything, making the appearance of all armor into that of swimwear. Appearance is restored through the use of a Restoration Stone. -->
		<set name="icon" val="BranchSys3.lcon.g_scrl_change_co_swimsuit_01" />
		<set name="immediate_effect" val="1" />
		<set name="handler" val="Book" />
		<set name="is_sellable" val="false" />
		<set name="default_action" val="skill_reduce" />
		<set name="etcitem_type" val="none" />
		<set name="is_stackable" val="true" />
		<set name="material" val="steel" />
		<set name="item_skill" val="18433-1" />
		<!-- Male Swimsuit No.1 Appearance Stone -->
	</item>
	<item id="46174" type="EtcItem" nameRu="Камень Обработки Мужского Купального Костюма No.2" nameEn="Male Swimsuit No.2 Appearance Stone">
		<!-- Позволяет изменить вид нагрудника на Мужской Купальный костюм No.2. Можно использовать на полном доспехе. Полностью изменяет облик доспехов. Камень восстановления возвращает предметам прежний вид. -->
		<!-- Changes the appearance of upper armor into that of Male Swimwear No. 2. Works on one-pieces too. It modifies everything, making the appearance of all armor into that of swimwear. Appearance is restored through the use of a Restoration Stone. -->
		<set name="icon" val="BranchSys3.lcon.g_scrl_change_co_swimsuit_01" />
		<set name="immediate_effect" val="1" />
		<set name="handler" val="Book" />
		<set name="is_sellable" val="false" />
		<set name="default_action" val="skill_reduce" />
		<set name="etcitem_type" val="none" />
		<set name="is_stackable" val="true" />
		<set name="material" val="steel" />
		<set name="item_skill" val="18434-1" />
		<!-- Male Swimsuit No.2 Appearance Stone -->
	</item>
	<item id="46175" type="EtcItem" nameRu="Камень Обработки Женского Купального Костюма No.1" nameEn="Bikini No.1 Appearance Stone">
		<!-- Позволяет изменить вид нагрудника на Женский Купальный костюм No.1. Можно использовать на полном доспехе. Полностью изменяет облик доспехов. Камень восстановления возвращает предметам прежний вид. -->
		<!-- Changes the appearance of upper armor into that of Bikini No. 1. Works on one-pieces too. It modifies everything, making the appearance of all armor into that of a bikini. Appearance is restored through the use of a Restoration Stone. -->
		<set name="icon" val="BranchSys3.lcon.g_scrl_change_co_swimsuit_01" />
		<set name="immediate_effect" val="1" />
		<set name="handler" val="Book" />
		<set name="is_sellable" val="false" />
		<set name="default_action" val="skill_reduce" />
		<set name="etcitem_type" val="none" />
		<set name="is_stackable" val="true" />
		<set name="material" val="steel" />
		<set name="item_skill" val="18435-1" />
		<!-- Bikini No.1 Appearance Stone -->
	</item>
	<item id="46176" type="EtcItem" nameRu="Камень Обработки Женского Купального Костюма No.2" nameEn="Bikini No.2 Appearance Stone">
		<!-- Позволяет изменить вид нагрудника на Женский Купальный костюм No.2. Можно использовать на полном доспехе. Полностью изменяет облик доспехов. Камень восстановления возвращает предметам прежний вид. -->
		<!-- Changes the appearance of upper armor into that of Bikini No. 2. Works on one-pieces too. It modifies everything, making the appearance of all armor into that of a bikini. Appearance is restored through the use of a Restoration Stone. -->
		<set name="icon" val="BranchSys3.lcon.g_scrl_change_co_swimsuit_01" />
		<set name="immediate_effect" val="1" />
		<set name="handler" val="Book" />
		<set name="is_sellable" val="false" />
		<set name="default_action" val="skill_reduce" />
		<set name="etcitem_type" val="none" />
		<set name="is_stackable" val="true" />
		<set name="material" val="steel" />
		<set name="item_skill" val="18436-1" />
		<!-- Bikini No.2 Appearance Stone -->
	</item>
	<item id="46177" type="EtcItem" nameRu="Сундук с Бутылью Души" nameEn="Soul Bottle Pack">
		<!-- В сундуке находится Бутыль Души Антарас/ Валакаса/ Королевы Муравьев/ Орфена/ Фринтезы/ Баюма. Будет удалена 19 ноября 2014 г. -->
		<!-- Wrapped Pack containing 1 bottle containing Antharas, Valakas, Queen Ant, Orfen, Frintezza, or Baium's soul. -->
		<set name="icon" val="icon.etc_elite_marguene_collection_box_i00" />
		<set name="is_sellable" val="false" />
		<set name="etcitem_type" val="scroll" />
		<set name="is_stackable" val="true" />
		<set name="material" val="paper" />
	</item>
	<item id="46178" type="EtcItem" nameRu="Небесный Коктейль" nameEn="Heavenly Cocktail">
		<!-- На 60 мин. дает эффекты 2-го уровня Поэмы Рога, Поэмы Гитары, Поэмы Органа и Поэмы Барабана. Время перезарядки: 60 мин. -->
		<!-- For 60 minutes, it receives the following level 2 effects: Horn Melody, Pipe Organ Melody, Guitar Melody, and Drum Melody. Cooldown is 60 min. -->
		<set name="icon" val="icon.etc_fruit_cocktail_i01" />
		<set name="is_tradable" val="false" />
		<set name="is_dropable" val="false" />
		<set name="is_sellable" val="false" />
		<set name="etcitem_type" val="potion" />
		<set name="is_stackable" val="true" />
		<set name="material" val="liquid" />
	</item>
	<item id="46179" type="Armor" nameRu="Мужской Купальный костюм No.1" nameEn="Male Swimwear No.1">
		<!-- Мужской Купальный костюм. -->
		<!-- Swimwear for male characters. -->
		<set name="icon" val="icon.london_olympic_bikini" />
		<set name="armor_type" val="heavy" />
		<set name="default_action" val="equip" />
		<set name="is_sellable" val="false" />
		<set name="weight" val="1000" />
		<set name="material" val="cloth" />
		<set name="bodypart" val="alldress" />
	</item>
	<item id="46180" type="Armor" nameRu="Мужской Купальный костюм No.2" nameEn="Male Swimwear No.2">
		<!-- Мужской Купальный костюм. -->
		<!-- Swimwear for male characters. -->
		<set name="icon" val="icon.london_olympic_bikini" />
		<set name="armor_type" val="heavy" />
		<set name="default_action" val="equip" />
		<set name="is_sellable" val="false" />
		<set name="weight" val="1000" />
		<set name="material" val="cloth" />
		<set name="bodypart" val="alldress" />
	</item>
	<item id="46181" type="Armor" nameRu="Женский Купальный костюм No.1" nameEn="Bikini No.1">
		<!-- Купальный костюм-бикини. -->
		<!-- Bikini for female characters. -->
		<set name="icon" val="icon.london_olympic_bikini" />
		<set name="armor_type" val="heavy" />
		<set name="default_action" val="equip" />
		<set name="is_sellable" val="false" />
		<set name="weight" val="1000" />
		<set name="material" val="cloth" />
		<set name="bodypart" val="alldress" />
	</item>
	<item id="46182" type="Armor" nameRu="Женский Купальный костюм No.2" nameEn="Bikini No.2">
		<!-- Закрытый женский купальный костюм. -->
		<!-- Bikini for female characters. -->
		<set name="icon" val="icon.london_olympic_bikini" />
		<set name="armor_type" val="heavy" />
		<set name="default_action" val="equip" />
		<set name="is_sellable" val="false" />
		<set name="weight" val="1000" />
		<set name="material" val="cloth" />
		<set name="bodypart" val="alldress" />
	</item>
	<item id="46183" type="EtcItem" nameRu="Подарочная Коробка Радости Дня Рождения" nameEn="Joyful Birthday Pack">
		<!-- Подарок, вручаемый Аллегрией на день рождения персонажа. При использовании можно получить 10 Зелий Дня Рождения и Колпак "С Днем Рождения!" -->
		<!-- A gift from Alegria for your character's birthday. Double-click to get 10 Happy Birthday Potions and a Birthday Hat. -->
		<set name="icon" val="icon.event_hero_treasure_box_i00" />
		<set name="weight" val="100" />
		<set name="is_tradable" val="false" />
		<set name="is_dropable" val="false" />
		<set name="is_sellable" val="false" />
		<set name="is_stackable" val="true" />
		<set name="material" val="paper" />
	</item>
	<item id="46184" type="EtcItem" nameRu="Зелье Дня Рождения" nameEn="Happy Birthday Potion">
		<!-- Восполняет 3/ 4 шкалы энергии. Время до повторного использования 60 мин. Нельзя использовать на Олимпиаде. На предмет не распространяется ограничение на количество использований энергетических предметов в неделю. -->
		<!-- 3 out of 4 bars on the vitality gauge are replenished. Cooldown is 60 minutes. Cannot be used in the Olympiad. -->
		<set name="icon" val="icon.etc_potion_blue_i00" />
		<set name="weight" val="80" />
		<set name="is_tradable" val="false" />
		<set name="is_dropable" val="false" />
		<set name="is_sellable" val="false" />
		<set name="etcitem_type" val="potion" />
		<set name="is_stackable" val="true" />
		<set name="material" val="liquid" />
	</item>
	<item id="46185" type="Armor" nameRu="Браслет Печати Агатиона - Барьер Святости Анаким" nameEn="Agathion - Anakim Holy Barrier">
		<!-- Позволяет призвать Агатиона Барьер Святости Анаким, состоящего из пяти сфер Анаким.  <Умения> 1. Усиление Параметров: СИЛ/ ИНТ/ ВЫН/ ЛВК/ МДР/ ДУХ +1. 2. Усиленная атака стихией: атака стихией огня/ воды/ земли/ ветра/ тьмы/ святости +30.  3. Благословение Анаким: бонус опыта и SP +3%. -->
		<!-- Summons Anakim Holy Barrier, which is comprised of 5 Anakim Spheres. <Item Skill>. 1. Balanced Power: STR/ INT/ CON/ DEX/ WIT/ MEN increases by 1. 2. Attribute Enchant: Fire/ Water/ Earth/ Wind/ Dark/ Holy Atk. increases by 30. 3. Anakim Blessing : Acquired XP and SP +3%. -->
		<set name="icon" val="BranchSys3.iconItem.g_agathion_anakim" />
		<set name="default_action" val="equip" />
		<set name="bodypart" val="lbracelet" />
		<set name="is_sellable" val="false" />
		<set name="weight" val="150" />
		<set name="material" val="silver" />
		<set name="item_skill" val="17551-1" />
		<!-- Balanced Power -->
		<set name="item_skill" val="17552-1" />
		<!-- Attribute Enchant -->
		<set name="item_skill" val="18442-1" />
		<!-- Anakim Blessing -->
		<set name="item_skill" val="18443-1" />
		<!-- Release Agathion's Seal - Anakaim Holy Barrier -->
		<set name="unequip_skill" val="3267-1" />
		<!-- Seal Agathion -->
	</item>
	<item id="46186" type="Armor" nameRu="Браслет Печати Агатиона - Барьер Святости Анаким" nameEn="Agathion - Anakim Holy Barrier">
		<!-- Позволяет призвать Агатиона Барьер Святости Анаким, состоящего из пяти сфер Анаким.  <Умения> 1. Усиление Параметров: СИЛ/ ИНТ/ ВЫН/ ЛВК/ МДР/ ДУХ +1. 2. Усиленная атака стихией: атака стихией огня/ воды/ земли/ ветра/ тьмы/ святости +30.  3. Благословение Анаким: бонус опыта и SP +3%. -->
		<!-- Summons Anakim Holy Barrier, which is comprised of 5 Anakim Spheres. <Item Skill>. 1. Balanced Power: STR/ INT/ CON/ DEX/ WIT/ MEN increases by 1. 2. Attribute Enchant: Fire/ Water/ Earth/ Wind/ Dark/ Holy Atk. increases by 30. 3. Anakim Blessing : Acquired XP and SP +3%. -->
		<set name="icon" val="BranchSys3.iconItem.g_agathion_anakim" />
		<set name="default_action" val="equip" />
		<set name="bodypart" val="lbracelet" />
		<set name="weight" val="150" />
		<set name="is_tradable" val="false" />
		<set name="is_dropable" val="false" />
		<set name="is_sellable" val="false" />
		<set name="time" val="43200" />
		<set name="material" val="silver" />
		<set name="item_skill" val="17551-1" />
		<!-- Balanced Power -->
		<set name="item_skill" val="17552-1" />
		<!-- Attribute Enchant -->
		<set name="item_skill" val="18442-1" />
		<!-- Anakim Blessing -->
		<set name="item_skill" val="18443-1" />
		<!-- Release Agathion's Seal - Anakaim Holy Barrier -->
		<set name="unequip_skill" val="3267-1" />
		<!-- Seal Agathion -->
	</item>
	<item id="46187" type="EtcItem" nameRu="Сундук Агатиона: Барьер Святости Анаким" nameEn="Agathion - Anakim Holy Barrier Pack">
		<!-- Открыв сундук, персонаж получит Брелок Агатиона - Барьер Святости Анаким (30 дн.) -->
		<!-- Wrapped Pack containing Holy Barrier Agathion Charm (30-day). -->
		<set name="icon" val="icon.event_high_oriental_park_i00" />
		<set name="default_action" val="peel" />
		<set name="immediate_effect" val="1" />
		<set name="weight" val="10" />
		<set name="is_stackable" val="true" />
		<set name="is_sellable" val="false" />
		<set name="time" val="43200" />
		<set name="handler" val="ExtractableItems" />
		<set name="material" val="paper" />
		<!-- Agathion - Anakim Holy Barrier - 30-day -->
		<set name="capsuled_items" val="46186,1,1,100" />
	</item>
	<item id="46188" type="EtcItem" nameRu="Сундук Агатиона: Барьер Святости Анаким" nameEn="Agathion - Anakim Holy Barrier Pack">
		<!-- Открыв сундук, персонаж получит Брелок Агатиона - Барьер Святости Анаким (30 дн.) или с низкой вероятностью Брелок Агатиона - Барьер Святости Анаким. -->
		<!-- Wrapped Pack containing an Anakim Holy Barrier Agathion Charm (30-day) or an Agathion Charm - Anakim Holy Barrier. -->
		<set name="icon" val="icon.event_high_oriental_park_i00" />
		<set name="default_action" val="capsule" />
		<set name="weight" val="10" />
		<set name="is_sellable" val="false" />
		<set name="is_stackable" val="true" />
		<set name="handler" val="ItemSkills" />
		<set name="immediate_effect" val="1" />
		<set name="material" val="paper" />
		<set name="item_skill" val="18438-1" />
		<!-- Agathion - Anakim Holy Barrier Pack -->
	</item>
	<item id="46189" type="EtcItem" nameRu="Камень Обработки Вампирского Стиля" nameEn="Vampiric Style Appearance Stone">
		<!-- Камень обработки, придающий доспехам облик Одеяния Вампира. Можно использовать с нагрудником или полным доспехом. Полностью изменяет облик доспехов.  -->
		<!-- Changes the appearace of your armor into that of a Vampiric Style. Can be used as a top or a one piece. It changes everything, making the appearance of all armor into that of a Vampiric Style. -->
		<set name="icon" val="BranchSys3.icon1.g_scrl_change_chest" />
		<set name="immediate_effect" val="1" />
		<set name="handler" val="Book" />
		<set name="is_sellable" val="false" />
		<set name="default_action" val="skill_reduce" />
		<set name="etcitem_type" val="none" />
		<set name="is_stackable" val="true" />
		<set name="material" val="steel" />
		<set name="item_skill" val="18440-1" />
		<!-- Vampiric Style Appearance Stone -->
	</item>
	<item id="46190" type="EtcItem" nameRu="Камень Обработки Вампирского Стиля" nameEn="Vampiric Style Appearance Stone">
		<!-- Камень обработки, придающий доспехам облик Одеяния Вампира на 30 д. Можно использовать с нагрудником или полным доспехом. Полностью изменяет облик доспехов.  -->
		<!-- Changes the appearance of your armor into that of a Vampiric Style. 30-day. Can be used as a top or a one piece. It changes everything, making the appearance of all armor into that of a Vampiric Style. -->
		<set name="icon" val="BranchSys3.icon1.g_scrl_change_chest" />
		<set name="immediate_effect" val="1" />
		<set name="handler" val="Book" />
		<set name="is_sellable" val="false" />
		<set name="default_action" val="skill_reduce" />
		<set name="etcitem_type" val="none" />
		<set name="is_stackable" val="true" />
		<set name="material" val="steel" />
		<set name="item_skill" val="18441-1" />
		<!-- Vampiric Style Appearance Stone -->
	</item>
	<item id="46191" type="EtcItem" nameRu="Сундук с Камнем Обработки Вампирского Стиля" nameEn="Vampiric Style Appearance Stone Pack">
		<!-- В сундуке находится Камень Обработки Вампирского Стиля (30 дн.); также с низкой вероятностью можно обнаружить Камень Обработки Вампирского Стиля.  -->
		<!-- Wrapped Pack containing a Vampiric Style Appearance Stone (30-day) or a Vampiric Style Appearance Stone. -->
		<set name="icon" val="icon.event_high_oriental_park_i00" />
		<set name="weight" val="10" />
		<set name="is_sellable" val="false" />
		<set name="is_stackable" val="true" />
		<set name="material" val="paper" />
	</item>
	<item id="46192" type="Armor" nameRu="Одеяние Вампира" nameEn="Vampiric Outfit">
		<!-- Вампирский наряд. -->
		<!-- Vampiric outfit. -->
		<set name="icon" val="BranchSys3.iconArmar.g_co_vampiric_u_i00" />
		<set name="is_sellable" val="false" />
		<set name="default_action" val="equip" />
		<set name="material" val="leather" />
		<set name="bodypart" val="alldress" />
	</item>
	<item id="46193" type="Armor" nameRu="Футболка Отражения Атаки " nameEn="Physical Reflect Shirt">
		<!-- Витаминный предмет Особая магическая футболка для Физ. Защ. Максимальная модификация до +10 при помощи Свитка Эйнхасад: Модифицировать Футболку. Начиная с модификации +4 повышает пассивные характеристики, при модификации на +5 и выше добавляются различные эффекты для Физ. Защ. -->
		<!-- Magic shirt for P. Def. Can be enchanted to +10 using Elemental Shirt Enchant Scrolls. When enchanted to +4 or more, passive and stats are increased. When enchanted to +5 or more, a P. Def. effect is given. -->
		<set name="icon" val="icon.reflect_attack_shirt" />
		<set name="default_action" val="equip" />
		<set name="bodypart" val="underwear" />
		<set name="is_tradable" val="false" />
		<set name="is_dropable" val="false" />
		<set name="is_sellable" val="false" />
		<set name="enchant_enabled" val="2" />
		<set name="weight" val="130" />
		<set name="material" val="crystal" />
		<skills>
			<skill id="18444" level="1" type="ENCHANT" value="5" /> <!-- Physical Reflect Shirt Enchant Effect -->
			<skill id="18444" level="2" type="ENCHANT" value="6" /> <!-- Physical Reflect Shirt Enchant Effect -->
			<skill id="18444" level="3" type="ENCHANT" value="7" /> <!-- Physical Reflect Shirt Enchant Effect -->
			<skill id="18444" level="4" type="ENCHANT" value="8" /> <!-- Physical Reflect Shirt Enchant Effect -->
			<skill id="18444" level="5" type="ENCHANT" value="9" /> <!-- Physical Reflect Shirt Enchant Effect -->
			<skill id="18444" level="6" type="ENCHANT" value="10" /> <!-- Physical Reflect Shirt Enchant Effect -->
		</skills>
		<for>
			<add order="0x10" stat="pDef" val="28" />
			<enchant order="0x0C" stat="pDef" val="0" />
		</for>
	</item>
	<item id="46194" type="Armor" nameRu="Футболка Отражения Магии" nameEn="Magical Reflect Shirt">
		<!-- Витаминный предмет Особая магическая футболка для Маг. Защ. Максимальная модификация до +10 при помощи Свитка Эйнхасад: Модифицировать Футболку. Начиная с модификации +4 повышает пассивные характеристики, при модификации на +5 и выше добавляются различные эффекты для Маг. Защ. -->
		<!-- Magic shirt for M. Def. Can be enchanted to +10 using Elemental Shirt Enchant Scrolls. When enchanted to +4 or more, passive and stats are increased. When enchanted to +5 or more, a M. Def. effect is given. -->
		<set name="icon" val="icon.reflect_magic_shirt" />
		<set name="default_action" val="equip" />
		<set name="bodypart" val="underwear" />
		<set name="is_tradable" val="false" />
		<set name="is_dropable" val="false" />
		<set name="is_sellable" val="false" />
		<set name="enchant_enabled" val="2" />
		<set name="weight" val="130" />
		<set name="material" val="crystal" />
		<skills>
			<skill id="18445" level="1" type="ENCHANT" value="5" /> <!-- Magical Reflect Shirt Enchant Effect -->
			<skill id="18445" level="2" type="ENCHANT" value="6" /> <!-- Magical Reflect Shirt Enchant Effect -->
			<skill id="18445" level="3" type="ENCHANT" value="7" /> <!-- Magical Reflect Shirt Enchant Effect -->
			<skill id="18445" level="4" type="ENCHANT" value="8" /> <!-- Magical Reflect Shirt Enchant Effect -->
			<skill id="18445" level="5" type="ENCHANT" value="9" /> <!-- Magical Reflect Shirt Enchant Effect -->
			<skill id="18445" level="6" type="ENCHANT" value="10" /> <!-- Magical Reflect Shirt Enchant Effect -->
		</skills>
		<for>
			<add order="0x10" stat="pDef" val="28" />
			<enchant order="0x0C" stat="pDef" val="0" />
		</for>
	</item>
	<item id="46195" type="EtcItem" nameRu="Сумка с Сияющей Футболкой Эйнхасад" nameEn="Shiny Elemental Shirt Bag">
		<!-- Дважды щелкните, чтобы получить Сияющую Футболку Эйнхасад (1 шт.) и Свиток Эйнхасад: Модифицировать Футболку (10 шт.) -->
		<!-- Double-click to get 1 Shiny Elemental Shirt and 10 Elemental Shirt Enchant Scrolls. -->
		<set name="icon" val="icon.ainharard_bac" />
		<set name="is_sellable" val="false" />
		<set name="is_stackable" val="true" />
		<set name="handler" val="ExtractableItems" />
		<set name="material" val="fish" />
		<!-- Shiny Elemental Shirt -->
		<!-- Scroll: Enchant Elemental Shirt -->
		<set name="capsuled_items" val="37718,1,1,100;25792,10,10,100" />
	</item>
	<item id="46196" type="EtcItem" nameRu="Сумка с Футболкой Отражения Атаки" nameEn="Reflect Attack Shirt Bag">
		<!-- Дважды щелкните, чтобы получить Футболку Отражения Атаки (1 шт.) и Свиток Эйнхасад: Модифицировать Футболку (10 шт.) -->
		<!-- Double-click to get 1 Physical Reflect Shirt and 10 Elemental Shirt Enchant Scrolls. -->
		<set name="icon" val="icon.reflect_attack_bac" />
		<set name="is_sellable" val="false" />
		<set name="is_stackable" val="true" />
		<set name="handler" val="ExtractableItems" />
		<set name="material" val="fish" />
		<!-- Physical Reflect Shirt -->
		<!-- Scroll: Enchant Elemental Shirt -->
		<set name="capsuled_items" val="46193,1,1,100;25792,10,10,100" />
	</item>
	<item id="46197" type="EtcItem" nameRu="Сумка с Футболкой Отражения Магии" nameEn="Reflect Magic Shirt Bag">
		<!-- Дважды щелкните, чтобы получить Футболку Отражения Магии (1 шт.) и Свиток Эйнхасад: Модифицировать Футболку (10 шт.) -->
		<!-- Double-click to get 1 Magical Reflect Shirt and 10 Elemental Shirt Enchant Scrolls. -->
		<set name="icon" val="icon.reflect_magic_bac" />
		<set name="is_sellable" val="false" />
		<set name="is_stackable" val="true" />
		<set name="handler" val="ExtractableItems" />
		<set name="material" val="fish" />
		<!-- Magical Reflect Shirt -->
		<!-- Scroll: Enchant Elemental Shirt -->
		<set name="capsuled_items" val="46194,1,1,100;25792,10,10,100" />
	</item>
	<item id="46198" type="EtcItem" nameRu="Золотая Медаль" nameEn="Gold Medal">
		<!-- Сверкающая медаль. За такую в торговой лавке хорошо заплатят. -->
		<!-- A shiny gold medal. Sell it at the shop for a lot of money. -->
		<set name="icon" val="icon.etc_event_medal_i00" />
		<set name="price" val="2000000000" />
		<set name="is_dropable" val="false" />
		<set name="is_destroyable" val="false" />
		<set name="is_stackable" val="true" />
		<set name="material" val="crystal" />
	</item>
	<item id="46199" type="EtcItem" nameRu="Камень Обработки Костюма для Хэллоуина" nameEn="Halloween Appearance Stone">
		<!-- Позволяет придать верхнему или полному доспеху внешний вид Костюма Хэллоуина. Полностью изменяет облик доспехов. -->
		<!-- Changes the appearance of a top armor or a one-piece into that of a Halloween outfit. It changes everything, making the appearance of all armor into that of the Halloween outfit. -->
		<set name="icon" val="BranchSys3.icon1.g_scrl_change_chest" />
		<set name="is_stackable" val="true" />
		<set name="is_sellable" val="false" />
		<set name="etcitem_type" val="none" />
		<set name="time" val="10080" />
		<set name="immediate_effect" val="1" />
		<set name="handler" val="Book" />
		<set name="default_action" val="skill_reduce" />
		<set name="material" val="steel" />
	</item>
</list>